Workbook

Sheet Hoja2
A1: Nível | B1: Nombre Maestro | C1: Paterno Maestro | D1: Materno Maestro | E1: Maestro | F1: Nombre | G1: Sexo | H1: correo
A2: LICENCIATURA | B2: AIDA CITLALI | C2: HERNANDEZ | D2: MONTAÑO | E2: HMA1841 | F2: HERNANDEZ MONTAÑO AIDA CITLALI | G2: FEMENINO | H2: aidacitlali.hernandezmontaño
A3: LICENCIATURA | B3: ALAM | C3: GOMEZ | D3: CANALES | E3: GCA1735 | F3: GOMEZ CANALES ALAM | G3: MASCULINO | H3: alam.gomezcanales
A4: LICENCIATURA | B4: ALDO EVERARDO | C4: GONZALEZ | D4: PULIDO | E4: GPA1916 | F4: GONZALEZ PULIDO ALDO EVERARDO | G4: MASCULINO | H4: aldoeverardo.gonzalezpulido
A5: LICENCIATURA | B5: ALDO MACIEL | C5: RUIZ | D5: AREVALO | E5: RAA1942 | F5: RUIZ AREVALO ALDO MACIEL | G5: MASCULINO | H5: aldomaciel.ruizarevalo
A6: LICENCIATURA | B6: ALEJANDRA | C6: CHAVEZ | D6: OSORIO | E6: COA1894 | F6: CHAVEZ OSORIO ALEJANDRA | G6: FEMENINO | H6: alejandra.chavezosorio
A7: LICENCIATURA | B7: ALEJANDRO | C7: URIBE | D7: LOPEZ | E7: ULA0927 | F7: URIBE LOPEZ ALEJANDRO | G7: MASCULINO | H7: alejandro.uribelopez
A8: LICENCIATURA | B8: ALFONSO | C8: ASCENCIO | D8: RUBIO | E8: ARA0918 | F8: ASCENCIO RUBIO ALFONSO | G8: MASCULINO | H8: alfonso.ascenciorubio
A9: LICENCIATURA | B9: ALFREDO | C9: GARCIA | D9: VALDERRAMA | E9: GVA1919 | F9: GARCIA VALDERRAMA ALFREDO | G9: MASCULINO | H9: alfredo.garciavalderrama
A10: LICENCIATURA | B10: ALFREDO DE JESUS | C10: VELAZQUEZ | D10: SANTOS | E10: VSA1861 | F10: VELAZQUEZ SANTOS ALFREDO DE JESUS | G10: MASCULINO | H10: alfredodejesus.velazquezsantos
A11: LICENCIATURA | B11: ALMA DANIELA | C11: VELAZQUEZ | D11: NAVARRETE | E11: VNA1925 | F11: VELAZQUEZ NAVARRETE ALMA DANIELA | G11: FEMENINO | H11: almadaniela.velazqueznavarrete
A12: LICENCIATURA | B12: ALVARO | C12: MORENO | D12: CORRAL | E12: MCA1844 | F12: MORENO CORRAL ALVARO | G12: MASCULINO | H12: alvaro.morenocorral
... A179: LICENCIATURA | B179: ZAIRA MARLENE | C179: ZAMBRANO | D179: LOPEZ | E179: ZLZ1862 | F179: ZAMBRANO LOPEZ ZAIRA MARLENE | G179: FEMENINO | H179: zairamarlene.zambranolopez

Sheet Hoja1
A1: Nível | B1: Carrera | C1: Grupo | D1: Nombre | E1: Materia | F1: Sexo
A2: LICENCIATURA | B2: MATERIAS INSTITUCIONALES | C2: TC 0503 1 | D2: LUNA HERRERA JOSE CARLOS | E2: CIUDADANIA Y DESARROLLO PROFESIONAL | F2: MASCULINO
A3: LICENCIATURA | B3: MATERIAS INSTITUCIONALES | C3: TC 0503 2 | D3: TAPIA VELAZQUEZ FRANCISCO | E3: CIUDADANIA Y DESARROLLO PROFESIONAL | F3: MASCULINO
A4: LICENCIATURA | B4: MATERIAS INSTITUCIONALES | C4: TC 0601 1 | D4: CHAN NUÑEZ MARIA ELENA | E4: ESCENARIO DE INTERVENCION SOCIAL I | F4: FEMENINO
A5: LICENCIATURA | B5: MATERIAS INSTITUCIONALES | C5: TC 0603 1 | D5: LUNA HERRERA JOSE CARLOS | E5: LIDERAZGO Y MANEJO DE GRUPOS | F5: MASCULINO
A6: LICENCIATURA | B6: MATERIAS INSTITUCIONALES | C6: TC 0801 | D6: CHAN NUÑEZ MARIA ELENA | E6: ESCENARIO DE INTERVENCION III | F6: FEMENINO
A7: LICENCIATURA | B7: MATERIAS INSTITUCIONALES | C7: TC0201 1 | D7: HERNANDEZ MONTAÑO AIDA CITLALI | E7: EXPERIENCIA DE ACCION SOCIAL | F7: FEMENINO
A8: LICENCIATURA | B8: MATERIAS INSTITUCIONALES | C8: TC0201 2 | D8: AGUILAR CEBALLOS CARLA MARIANA | E8: EXPERIENCIA DE ACCION SOCIAL | F8: FEMENINO
A9: LICENCIATURA | B9: MATERIAS INSTITUCIONALES | C9: TC0201 3 | D9: FARIAS CASTELLANOS ISIS | E9: EXPERIENCIA DE ACCION SOCIAL | F9: FEMENINO
A10: LICENCIATURA | B10: MATERIAS INSTITUCIONALES | C10: TC0201 4 | D10: CASILLAS MORA MONICA DANIELA | E10: EXPERIENCIA DE ACCION SOCIAL | F10: FEMENINO
A11: LICENCIATURA | B11: MATERIAS INSTITUCIONALES | C11: TC0201 5 | D11: HERNANDEZ MONTAÑO AIDA CITLALI | E11: EXPERIENCIA DE ACCION SOCIAL | F11: FEMENINO
A12: LICENCIATURA | B12: MATERIAS INSTITUCIONALES | C12: TC0201 6 | D12: AGUILAR CEBALLOS CARLA MARIANA | E12: EXPERIENCIA DE ACCION SOCIAL | F12: FEMENINO
... A329: LICENCIATURA | B329: PSICOLOGIA | C329: PSI 8° | D329: SALCEDO ROSALES ERIKA IVETTE | E329: TENDENCIAS CONTEMPORANEAS DE LA PSICOLOGIA | F329: FEMENINO

Sheet PARTICIPANTES
A1: id | B1: Nivel | C1: Correo | D1: matricula | E1: clave | F1: Nombre | G1: carrera | H1: grado | I1: sexo | J1: situacion | K1: =CONCATENATE("INSERT INTO participantes (",L1,") VALUES (") -> INSERT INTO participantes (id,nivel,correo,matricula,clave,nombre,carrera,grado,sexo,situacion,evaluados,num_evaluados,total_evaluaciones,ultimo_acceso,nivel_acceso) VALUES ( | L1: id,nivel,correo,matricula,clave,nombre,carrera,grado,sexo,situacion,evaluados,num_evaluados,total_evaluaciones,ultimo_acceso,nivel_acceso
A2: 2001 | B2: 'LICENCIATURA' | C2: =Hoja2!H2 -> aidacitlali.hernandezmontaño | D2: =Hoja2!E2 -> HMA1841 | E2: TOMAR DEL SND' | F2: =Hoja2!F2 -> HERNANDEZ MONTAÑO AIDA CITLALI | G2: PROFESORES | I2: =Hoja2!G2 -> FEMENINO | K2: =CONCATENATE(A2,",",B2,",'",C2,"','",D2,"','",E2,",'",F2,"','",G2,"','",H2,"','",UPPER(I2),"','",UPPER(J2),"','',0,0,'','PROFESOR'") -> 2001,'LICENCIATURA','aidacitlali.hernandezmontaño','HMA1841','TOMAR DEL SND','HERNANDEZ MONTAÑO AIDA CITLALI','PROFESORES','','FEMENINO','','',0,0,'','PROFESOR' | L2: =CONCATENATE($K$1,K2,");") -> INSERT INTO participantes (id,nivel,correo,matricula,clave,nombre,carrera,grado,sexo,situacion,evaluados,num_evaluados,total_evaluaciones,ultimo_acceso,nivel_acceso) VALUES (2001,'LICENCIATURA','aidacitlali.hernandezmontaño','HMA1841','TOMAR DEL SND','HERNANDEZ MONTAÑO AIDA CITLALI','PROFESORES','','FEMENINO','','',0,0,'','PROFESOR');
A3: =A2+1 -> 2002 | B3: 'LICENCIATURA' | C3: =Hoja2!H3 -> alam.gomezcanales | D3: =Hoja2!E3 -> GCA1735 | E3: TOMAR DEL SND' | F3: =Hoja2!F3 -> GOMEZ CANALES ALAM | G3: PROFESORES | I3: =Hoja2!G3 -> MASCULINO | K3: =CONCATENATE(A3,",",B3,",'",C3,"','",D3,"','",E3,",'",F3,"','",G3,"','",H3,"','",UPPER(I3),"','",UPPER(J3),"','',0,0,'','PROFESOR'") -> 2002,'LICENCIATURA','alam.gomezcanales','GCA1735','TOMAR DEL SND','GOMEZ CANALES ALAM','PROFESORES','','MASCULINO','','',0,0,'','PROFESOR' | L3: =CONCATENATE($K$1,K3,");") -> INSERT INTO participantes (id,nivel,correo,matricula,clave,nombre,carrera,grado,sexo,situacion,evaluados,num_evaluados,total_evaluaciones,ultimo_acceso,nivel_acceso) VALUES (2002,'LICENCIATURA','alam.gomezcanales','GCA1735','TOMAR DEL SND','GOMEZ CANALES ALAM','PROFESORES','','MASCULINO','','',0,0,'','PROFESOR');
A4: =A3+1 -> 2003 | B4: 'LICENCIATURA' | C4: =Hoja2!H4 -> aldoeverardo.gonzalezpulido | D4: =Hoja2!E4 -> GPA1916 | E4: TOMAR DEL SND' | F4: =Hoja2!F4 -> GONZALEZ PULIDO ALDO EVERARDO | G4: PROFESORES | I4: =Hoja2!G4 -> MASCULINO | K4: =CONCATENATE(A4,",",B4,",'",C4,"','",D4,"','",E4,",'",F4,"','",G4,"','",H4,"','",UPPER(I4),"','",UPPER(J4),"','',0,0,'','PROFESOR'") -> 2003,'LICENCIATURA','aldoeverardo.gonzalezpulido','GPA1916','TOMAR DEL SND','GONZALEZ PULIDO ALDO EVERARDO','PROFESORES','','MASCULINO','','',0,0,'','PROFESOR' | L4: =CONCATENATE($K$1,K4,");") -> INSERT INTO participantes (id,nivel,correo,matricula,clave,nombre,carrera,grado,sexo,situacion,evaluados,num_evaluados,total_evaluaciones,ultimo_acceso,nivel_acceso) VALUES (2003,'LICENCIATURA','aldoeverardo.gonzalezpulido','GPA1916','TOMAR DEL SND','GONZALEZ PULIDO ALDO EVERARDO','PROFESORES','','MASCULINO','','',0,0,'','PROFESOR');
A5: =A4+1 -> 2004 | B5: 'LICENCIATURA' | C5: =Hoja2!H5 -> aldomaciel.ruizarevalo | D5: =Hoja2!E5 -> RAA1942 | E5: TOMAR DEL SND' | F5: =Hoja2!F5 -> RUIZ AREVALO ALDO MACIEL | G5: PROFESORES | I5: =Hoja2!G5 -> MASCULINO | K5: =CONCATENATE(A5,",",B5,",'",C5,"','",D5,"','",E5,",'",F5,"','",G5,"','",H5,"','",UPPER(I5),"','",UPPER(J5),"','',0,0,'','PROFESOR'") -> 2004,'LICENCIATURA','aldomaciel.ruizarevalo','RAA1942','TOMAR DEL SND','RUIZ AREVALO ALDO MACIEL','PROFESORES','','MASCULINO','','',0,0,'','PROFESOR' | L5: =CONCATENATE($K$1,K5,");") -> INSERT INTO participantes (id,nivel,correo,matricula,clave,nombre,carrera,grado,sexo,situacion,evaluados,num_evaluados,total_evaluaciones,ultimo_acceso,nivel_acceso) VALUES (2004,'LICENCIATURA','aldomaciel.ruizarevalo','RAA1942','TOMAR DEL SND','RUIZ AREVALO ALDO MACIEL','PROFESORES','','MASCULINO','','',0,0,'','PROFESOR');
A6: =A5+1 -> 2005 | B6: 'LICENCIATURA' | C6: =Hoja2!H6 -> alejandra.chavezosorio | D6: =Hoja2!E6 -> COA1894 | E6: TOMAR DEL SND' | F6: =Hoja2!F6 -> CHAVEZ OSORIO ALEJANDRA | G6: PROFESORES | I6: =Hoja2!G6 -> FEMENINO | K6: =CONCATENATE(A6,",",B6,",'",C6,"','",D6,"','",E6,",'",F6,"','",G6,"','",H6,"','",UPPER(I6),"','",UPPER(J6),"','',0,0,'','PROFESOR'") -> 2005,'LICENCIATURA','alejandra.chavezosorio','COA1894','TOMAR DEL SND','CHAVEZ OSORIO ALEJANDRA','PROFESORES','','FEMENINO','','',0,0,'','PROFESOR' | L6: =CONCATENATE($K$1,K6,");") -> INSERT INTO participantes (id,nivel,correo,matricula,clave,nombre,carrera,grado,sexo,situacion,evaluados,num_evaluados,total_evaluaciones,ultimo_acceso,nivel_acceso) VALUES (2005,'LICENCIATURA','alejandra.chavezosorio','COA1894','TOMAR DEL SND','CHAVEZ OSORIO ALEJANDRA','PROFESORES','','FEMENINO','','',0,0,'','PROFESOR');
A7: =A6+1 -> 2006 | B7: 'LICENCIATURA' | C7: =Hoja2!H7 -> alejandro.uribelopez | D7: =Hoja2!E7 -> ULA0927 | E7: TOMAR DEL SND' | F7: =Hoja2!F7 -> URIBE LOPEZ ALEJANDRO | G7: PROFESORES | I7: =Hoja2!G7 -> MASCULINO | K7: =CONCATENATE(A7,",",B7,",'",C7,"','",D7,"','",E7,",'",F7,"','",G7,"','",H7,"','",UPPER(I7),"','",UPPER(J7),"','',0,0,'','PROFESOR'") -> 2006,'LICENCIATURA','alejandro.uribelopez','ULA0927','TOMAR DEL SND','URIBE LOPEZ ALEJANDRO','PROFESORES','','MASCULINO','','',0,0,'','PROFESOR' | L7: =CONCATENATE($K$1,K7,");") -> INSERT INTO participantes (id,nivel,correo,matricula,clave,nombre,carrera,grado,sexo,situacion,evaluados,num_evaluados,total_evaluaciones,ultimo_acceso,nivel_acceso) VALUES (2006,'LICENCIATURA','alejandro.uribelopez','ULA0927','TOMAR DEL SND','URIBE LOPEZ ALEJANDRO','PROFESORES','','MASCULINO','','',0,0,'','PROFESOR');
A8: =A7+1 -> 2007 | B8: 'LICENCIATURA' | C8: =Hoja2!H8 -> alfonso.ascenciorubio | D8: =Hoja2!E8 -> ARA0918 | E8: TOMAR DEL SND' | F8: =Hoja2!F8 -> ASCENCIO RUBIO ALFONSO | G8: PROFESORES | I8: =Hoja2!G8 -> MASCULINO | K8: =CONCATENATE(A8,",",B8,",'",C8,"','",D8,"','",E8,",'",F8,"','",G8,"','",H8,"','",UPPER(I8),"','",UPPER(J8),"','',0,0,'','PROFESOR'") -> 2007,'LICENCIATURA','alfonso.ascenciorubio','ARA0918','TOMAR DEL SND','ASCENCIO RUBIO ALFONSO','PROFESORES','','MASCULINO','','',0,0,'','PROFESOR' | L8: =CONCATENATE($K$1,K8,");") -> INSERT INTO participantes (id,nivel,correo,matricula,clave,nombre,carrera,grado,sexo,situacion,evaluados,num_evaluados,total_evaluaciones,ultimo_acceso,nivel_acceso) VALUES (2007,'LICENCIATURA','alfonso.ascenciorubio','ARA0918','TOMAR DEL SND','ASCENCIO RUBIO ALFONSO','PROFESORES','','MASCULINO','','',0,0,'','PROFESOR');
A9: =A8+1 -> 2008 | B9: 'LICENCIATURA' | C9: =Hoja2!H9 -> alfredo.garciavalderrama | D9: =Hoja2!E9 -> GVA1919 | E9: TOMAR DEL SND' | F9: =Hoja2!F9 -> GARCIA VALDERRAMA ALFREDO | G9: PROFESORES | I9: =Hoja2!G9 -> MASCULINO | K9: =CONCATENATE(A9,",",B9,",'",C9,"','",D9,"','",E9,",'",F9,"','",G9,"','",H9,"','",UPPER(I9),"','",UPPER(J9),"','',0,0,'','PROFESOR'") -> 2008,'LICENCIATURA','alfredo.garciavalderrama','GVA1919','TOMAR DEL SND','GARCIA VALDERRAMA ALFREDO','PROFESORES','','MASCULINO','','',0,0,'','PROFESOR' | L9: =CONCATENATE($K$1,K9,");") -> INSERT INTO participantes (id,nivel,correo,matricula,clave,nombre,carrera,grado,sexo,situacion,evaluados,num_evaluados,total_evaluaciones,ultimo_acceso,nivel_acceso) VALUES (2008,'LICENCIATURA','alfredo.garciavalderrama','GVA1919','TOMAR DEL SND','GARCIA VALDERRAMA ALFREDO','PROFESORES','','MASCULINO','','',0,0,'','PROFESOR');
A10: =A9+1 -> 2009 | B10: 'LICENCIATURA' | C10: =Hoja2!H10 -> alfredodejesus.velazquezsantos | D10: =Hoja2!E10 -> VSA1861 | E10: TOMAR DEL SND' | F10: =Hoja2!F10 -> VELAZQUEZ SANTOS ALFREDO DE JESUS | G10: PROFESORES | I10: =Hoja2!G10 -> MASCULINO | K10: =CONCATENATE(A10,",",B10,",'",C10,"','",D10,"','",E10,",'",F10,"','",G10,"','",H10,"','",UPPER(I10),"','",UPPER(J10),"','',0,0,'','PROFESOR'") -> 2009,'LICENCIATURA','alfredodejesus.velazquezsantos','VSA1861','TOMAR DEL SND','VELAZQUEZ SANTOS ALFREDO DE JESUS','PROFESORES','','MASCULINO','','',0,0,'','PROFESOR' | L10: =CONCATENATE($K$1,K10,");") -> INSERT INTO participantes (id,nivel,correo,matricula,clave,nombre,carrera,grado,sexo,situacion,evaluados,num_evaluados,total_evaluaciones,ultimo_acceso,nivel_acceso) VALUES (2009,'LICENCIATURA','alfredodejesus.velazquezsantos','VSA1861','TOMAR DEL SND','VELAZQUEZ SANTOS ALFREDO DE JESUS','PROFESORES','','MASCULINO','','',0,0,'','PROFESOR');
A11: =A10+1 -> 2010 | B11: 'LICENCIATURA' | C11: =Hoja2!H11 -> almadaniela.velazqueznavarrete | D11: =Hoja2!E11 -> VNA1925 | E11: TOMAR DEL SND' | F11: =Hoja2!F11 -> VELAZQUEZ NAVARRETE ALMA DANIELA | G11: PROFESORES | I11: =Hoja2!G11 -> FEMENINO | K11: =CONCATENATE(A11,",",B11,",'",C11,"','",D11,"','",E11,",'",F11,"','",G11,"','",H11,"','",UPPER(I11),"','",UPPER(J11),"','',0,0,'','PROFESOR'") -> 2010,'LICENCIATURA','almadaniela.velazqueznavarrete','VNA1925','TOMAR DEL SND','VELAZQUEZ NAVARRETE ALMA DANIELA','PROFESORES','','FEMENINO','','',0,0,'','PROFESOR' | L11: =CONCATENATE($K$1,K11,");") -> INSERT INTO participantes (id,nivel,correo,matricula,clave,nombre,carrera,grado,sexo,situacion,evaluados,num_evaluados,total_evaluaciones,ultimo_acceso,nivel_acceso) VALUES (2010,'LICENCIATURA','almadaniela.velazqueznavarrete','VNA1925','TOMAR DEL SND','VELAZQUEZ NAVARRETE ALMA DANIELA','PROFESORES','','FEMENINO','','',0,0,'','PROFESOR');
A12: =A11+1 -> 2011 | B12: 'LICENCIATURA' | C12: =Hoja2!H12 -> alvaro.morenocorral | D12: =Hoja2!E12 -> MCA1844 | E12: TOMAR DEL SND' | F12: =Hoja2!F12 -> MORENO CORRAL ALVARO | G12: PROFESORES | I12: =Hoja2!G12 -> MASCULINO | K12: =CONCATENATE(A12,",",B12,",'",C12,"','",D12,"','",E12,",'",F12,"','",G12,"','",H12,"','",UPPER(I12),"','",UPPER(J12),"','',0,0,'','PROFESOR'") -> 2011,'LICENCIATURA','alvaro.morenocorral','MCA1844','TOMAR DEL SND','MORENO CORRAL ALVARO','PROFESORES','','MASCULINO','','',0,0,'','PROFESOR' | L12: =CONCATENATE($K$1,K12,");") -> INSERT INTO participantes (id,nivel,correo,matricula,clave,nombre,carrera,grado,sexo,situacion,evaluados,num_evaluados,total_evaluaciones,ultimo_acceso,nivel_acceso) VALUES (2011,'LICENCIATURA','alvaro.morenocorral','MCA1844','TOMAR DEL SND','MORENO CORRAL ALVARO','PROFESORES','','MASCULINO','','',0,0,'','PROFESOR');
A13: =A12+1 -> 2012 | B13: 'LICENCIATURA' | C13: =Hoja2!H13 -> alvaro.pujolbecerra | D13: =Hoja2!E13 -> PBA1849 | E13: TOMAR DEL SND' | F13: =Hoja2!F13 -> PUJOL BECERRA ALVARO | G13: PROFESORES | I13: =Hoja2!G13 -> MASCULINO | K13: =CONCATENATE(A13,",",B13,",'",C13,"','",D13,"','",E13,",'",F13,"','",G13,"','",H13,"','",UPPER(I13),"','",UPPER(J13),"','',0,0,'','PROFESOR'") -> 2012,'LICENCIATURA','alvaro.pujolbecerra','PBA1849','TOMAR DEL SND','PUJOL BECERRA ALVARO','PROFESORES','','MASCULINO','','',0,0,'','PROFESOR' | L13: =CONCATENATE($K$1,K13,");") -> INSERT INTO participantes (id,nivel,correo,matricula,clave,nombre,carrera,grado,sexo,situacion,evaluados,num_evaluados,total_evaluaciones,ultimo_acceso,nivel_acceso) VALUES (2012,'LICENCIATURA','alvaro.pujolbecerra','PBA1849','TOMAR DEL SND','PUJOL BECERRA ALVARO','PROFESORES','','MASCULINO','','',0,0,'','PROFESOR');
A14: =A13+1 -> 2013 | B14: 'LICENCIATURA' | C14: =Hoja2!H14 -> amandajanette.renteriajimenez | D14: =Hoja2!E14 -> RJA1850 | E14: TOMAR DEL SND' | F14: =Hoja2!F14 -> RENTERIA JIMENEZ AMANDA JANETTE | G14: PROFESORES | I14: =Hoja2!G14 -> FEMENINO | K14: =CONCATENATE(A14,",",B14,",'",C14,"','",D14,"','",E14,",'",F14,"','",G14,"','",H14,"','",UPPER(I14),"','",UPPER(J14),"','',0,0,'','PROFESOR'") -> 2013,'LICENCIATURA','amandajanette.renteriajimenez','RJA1850','TOMAR DEL SND','RENTERIA JIMENEZ AMANDA JANETTE','PROFESORES','','FEMENINO','','',0,0,'','PROFESOR' | L14: =CONCATENATE($K$1,K14,");") -> INSERT INTO participantes (id,nivel,correo,matricula,clave,nombre,carrera,grado,sexo,situacion,evaluados,num_evaluados,total_evaluaciones,ultimo_acceso,nivel_acceso) VALUES (2013,'LICENCIATURA','amandajanette.renteriajimenez','RJA1850','TOMAR DEL SND','RENTERIA JIMENEZ AMANDA JANETTE','PROFESORES','','FEMENINO','','',0,0,'','PROFESOR');
... A179: =A178+1 -> 2178 | B179: 'LICENCIATURA' | C179: =Hoja2!H179 -> zairamarlene.zambranolopez | D179: =Hoja2!E179 -> ZLZ1862 | E179: TOMAR DEL SND' | F179: =Hoja2!F179 -> ZAMBRANO LOPEZ ZAIRA MARLENE | G179: PROFESORES | I179: =Hoja2!G179 -> FEMENINO | K179: =CONCATENATE(A179,",",B179,",'",C179,"','",D179,"','",E179,",'",F179,"','",G179,"','",H179,"','",UPPER(I179),"','",UPPER(J179),"','',0,0,'','PROFESOR'") -> 2178,'LICENCIATURA','zairamarlene.zambranolopez','ZLZ1862','TOMAR DEL SND','ZAMBRANO LOPEZ ZAIRA MARLENE','PROFESORES','','FEMENINO','','',0,0,'','PROFESOR' | L179: =CONCATENATE($K$1,K179,");") -> INSERT INTO participantes (id,nivel,correo,matricula,clave,nombre,carrera,grado,sexo,situacion,evaluados,num_evaluados,total_evaluaciones,ultimo_acceso,nivel_acceso) VALUES (2178,'LICENCIATURA','zairamarlene.zambranolopez','ZLZ1862','TOMAR DEL SND','ZAMBRANO LOPEZ ZAIRA MARLENE','PROFESORES','','FEMENINO','','',0,0,'','PROFESOR');

Sheet Materias
A1: ID | B1: NIVEL | C1: Carrera | D1: Grupo | E1: Nombre | F1: Materia | G1: Sexo | H1: SELLO | I1: INSERT INTO profesores (id,nivel,carrera,grupo,nombre,materia,sexo,sello) VALUES (
A2: 1001 | B2: LICENCIATURA | C2: =Hoja1!B2 -> MATERIAS INSTITUCIONALES | D2: TC 0503 1' | E2: =Hoja1!D2 -> LUNA HERRERA JOSE CARLOS | F2: =Hoja1!E2 -> CIUDADANIA Y DESARROLLO PROFESIONAL | G2: =Hoja1!F2 -> MASCULINO | H2: =IF(C2="MATERIAS INSTITUCIONALES",1,0) -> 1 | I2: =CONCATENATE(A2,",'",B2,"','",C2,"','",D2,",'",E2,"','",F2,"','",G2,"',",H2) -> 1001,'LICENCIATURA','MATERIAS INSTITUCIONALES','TC 0503 1','LUNA HERRERA JOSE CARLOS','CIUDADANIA Y DESARROLLO PROFESIONAL','MASCULINO',1 | J2: =CONCATENATE($I$1,I2,");") -> INSERT INTO profesores (id,nivel,carrera,grupo,nombre,materia,sexo,sello) VALUES (1001,'LICENCIATURA','MATERIAS INSTITUCIONALES','TC 0503 1','LUNA HERRERA JOSE CARLOS','CIUDADANIA Y DESARROLLO PROFESIONAL','MASCULINO',1);
A3: =A2+1 -> 1002 | B3: LICENCIATURA | C3: =Hoja1!B3 -> MATERIAS INSTITUCIONALES | D3: TC 0503 2' | E3: =Hoja1!D3 -> TAPIA VELAZQUEZ FRANCISCO | F3: =Hoja1!E3 -> CIUDADANIA Y DESARROLLO PROFESIONAL | G3: =Hoja1!F3 -> MASCULINO | H3: =IF(C3="MATERIAS INSTITUCIONALES",1,0) -> 1 | I3: =CONCATENATE(A3,",'",B3,"','",C3,"','",D3,",'",E3,"','",F3,"','",G3,"',",H3) -> 1002,'LICENCIATURA','MATERIAS INSTITUCIONALES','TC 0503 2','TAPIA VELAZQUEZ FRANCISCO','CIUDADANIA Y DESARROLLO PROFESIONAL','MASCULINO',1 | J3: =CONCATENATE($I$1,I3,");") -> INSERT INTO profesores (id,nivel,carrera,grupo,nombre,materia,sexo,sello) VALUES (1002,'LICENCIATURA','MATERIAS INSTITUCIONALES','TC 0503 2','TAPIA VELAZQUEZ FRANCISCO','CIUDADANIA Y DESARROLLO PROFESIONAL','MASCULINO',1);
A4: =A3+1 -> 1003 | B4: LICENCIATURA | C4: =Hoja1!B4 -> MATERIAS INSTITUCIONALES | D4: TC 0601 1' | E4: =Hoja1!D4 -> CHAN NUÑEZ MARIA ELENA | F4: =Hoja1!E4 -> ESCENARIO DE INTERVENCION SOCIAL I | G4: =Hoja1!F4 -> FEMENINO | H4: =IF(C4="MATERIAS INSTITUCIONALES",1,0) -> 1 | I4: =CONCATENATE(A4,",'",B4,"','",C4,"','",D4,",'",E4,"','",F4,"','",G4,"',",H4) -> 1003,'LICENCIATURA','MATERIAS INSTITUCIONALES','TC 0601 1','CHAN NUÑEZ MARIA ELENA','ESCENARIO DE INTERVENCION SOCIAL I','FEMENINO',1 | J4: =CONCATENATE($I$1,I4,");") -> INSERT INTO profesores (id,nivel,carrera,grupo,nombre,materia,sexo,sello) VALUES (1003,'LICENCIATURA','MATERIAS INSTITUCIONALES','TC 0601 1','CHAN NUÑEZ MARIA ELENA','ESCENARIO DE INTERVENCION SOCIAL I','FEMENINO',1);
A5: =A4+1 -> 1004 | B5: LICENCIATURA | C5: =Hoja1!B5 -> MATERIAS INSTITUCIONALES | D5: TC 0603 1' | E5: =Hoja1!D5 -> LUNA HERRERA JOSE CARLOS | F5: =Hoja1!E5 -> LIDERAZGO Y MANEJO DE GRUPOS | G5: =Hoja1!F5 -> MASCULINO | H5: =IF(C5="MATERIAS INSTITUCIONALES",1,0) -> 1 | I5: =CONCATENATE(A5,",'",B5,"','",C5,"','",D5,",'",E5,"','",F5,"','",G5,"',",H5) -> 1004,'LICENCIATURA','MATERIAS INSTITUCIONALES','TC 0603 1','LUNA HERRERA JOSE CARLOS','LIDERAZGO Y MANEJO DE GRUPOS','MASCULINO',1 | J5: =CONCATENATE($I$1,I5,");") -> INSERT INTO profesores (id,nivel,carrera,grupo,nombre,materia,sexo,sello) VALUES (1004,'LICENCIATURA','MATERIAS INSTITUCIONALES','TC 0603 1','LUNA HERRERA JOSE CARLOS','LIDERAZGO Y MANEJO DE GRUPOS','MASCULINO',1);
A6: =A5+1 -> 1005 | B6: LICENCIATURA | C6: =Hoja1!B6 -> MATERIAS INSTITUCIONALES | D6: TC 0801' | E6: =Hoja1!D6 -> CHAN NUÑEZ MARIA ELENA | F6: =Hoja1!E6 -> ESCENARIO DE INTERVENCION III | G6: =Hoja1!F6 -> FEMENINO | H6: =IF(C6="MATERIAS INSTITUCIONALES",1,0) -> 1 | I6: =CONCATENATE(A6,",'",B6,"','",C6,"','",D6,",'",E6,"','",F6,"','",G6,"',",H6) -> 1005,'LICENCIATURA','MATERIAS INSTITUCIONALES','TC 0801','CHAN NUÑEZ MARIA ELENA','ESCENARIO DE INTERVENCION III','FEMENINO',1 | J6: =CONCATENATE($I$1,I6,");") -> INSERT INTO profesores (id,nivel,carrera,grupo,nombre,materia,sexo,sello) VALUES (1005,'LICENCIATURA','MATERIAS INSTITUCIONALES','TC 0801','CHAN NUÑEZ MARIA ELENA','ESCENARIO DE INTERVENCION III','FEMENINO',1);
A7: =A6+1 -> 1006 | B7: LICENCIATURA | C7: =Hoja1!B7 -> MATERIAS INSTITUCIONALES | D7: TC0201 1' | E7: =Hoja1!D7 -> HERNANDEZ MONTAÑO AIDA CITLALI | F7: =Hoja1!E7 -> EXPERIENCIA DE ACCION SOCIAL | G7: =Hoja1!F7 -> FEMENINO | H7: =IF(C7="MATERIAS INSTITUCIONALES",1,0) -> 1 | I7: =CONCATENATE(A7,",'",B7,"','",C7,"','",D7,",'",E7,"','",F7,"','",G7,"',",H7) -> 1006,'LICENCIATURA','MATERIAS INSTITUCIONALES','TC0201 1','HERNANDEZ MONTAÑO AIDA CITLALI','EXPERIENCIA DE ACCION SOCIAL','FEMENINO',1 | J7: =CONCATENATE($I$1,I7,");") -> INSERT INTO profesores (id,nivel,carrera,grupo,nombre,materia,sexo,sello) VALUES (1006,'LICENCIATURA','MATERIAS INSTITUCIONALES','TC0201 1','HERNANDEZ MONTAÑO AIDA CITLALI','EXPERIENCIA DE ACCION SOCIAL','FEMENINO',1);
A8: =A7+1 -> 1007 | B8: LICENCIATURA | C8: =Hoja1!B8 -> MATERIAS INSTITUCIONALES | D8: TC0201 2' | E8: =Hoja1!D8 -> AGUILAR CEBALLOS CARLA MARIANA | F8: =Hoja1!E8 -> EXPERIENCIA DE ACCION SOCIAL | G8: =Hoja1!F8 -> FEMENINO | H8: =IF(C8="MATERIAS INSTITUCIONALES",1,0) -> 1 | I8: =CONCATENATE(A8,",'",B8,"','",C8,"','",D8,",'",E8,"','",F8,"','",G8,"',",H8) -> 1007,'LICENCIATURA','MATERIAS INSTITUCIONALES','TC0201 2','AGUILAR CEBALLOS CARLA MARIANA','EXPERIENCIA DE ACCION SOCIAL','FEMENINO',1 | J8: =CONCATENATE($I$1,I8,");") -> INSERT INTO profesores (id,nivel,carrera,grupo,nombre,materia,sexo,sello) VALUES (1007,'LICENCIATURA','MATERIAS INSTITUCIONALES','TC0201 2','AGUILAR CEBALLOS CARLA MARIANA','EXPERIENCIA DE ACCION SOCIAL','FEMENINO',1);
A9: =A8+1 -> 1008 | B9: LICENCIATURA | C9: =Hoja1!B9 -> MATERIAS INSTITUCIONALES | D9: TC0201 3' | E9: =Hoja1!D9 -> FARIAS CASTELLANOS ISIS | F9: =Hoja1!E9 -> EXPERIENCIA DE ACCION SOCIAL | G9: =Hoja1!F9 -> FEMENINO | H9: =IF(C9="MATERIAS INSTITUCIONALES",1,0) -> 1 | I9: =CONCATENATE(A9,",'",B9,"','",C9,"','",D9,",'",E9,"','",F9,"','",G9,"',",H9) -> 1008,'LICENCIATURA','MATERIAS INSTITUCIONALES','TC0201 3','FARIAS CASTELLANOS ISIS','EXPERIENCIA DE ACCION SOCIAL','FEMENINO',1 | J9: =CONCATENATE($I$1,I9,");") -> INSERT INTO profesores (id,nivel,carrera,grupo,nombre,materia,sexo,sello) VALUES (1008,'LICENCIATURA','MATERIAS INSTITUCIONALES','TC0201 3','FARIAS CASTELLANOS ISIS','EXPERIENCIA DE ACCION SOCIAL','FEMENINO',1);
A10: =A9+1 -> 1009 | B10: LICENCIATURA | C10: =Hoja1!B10 -> MATERIAS INSTITUCIONALES | D10: TC0201 4' | E10: =Hoja1!D10 -> CASILLAS MORA MONICA DANIELA | F10: =Hoja1!E10 -> EXPERIENCIA DE ACCION SOCIAL | G10: =Hoja1!F10 -> FEMENINO | H10: =IF(C10="MATERIAS INSTITUCIONALES",1,0) -> 1 | I10: =CONCATENATE(A10,",'",B10,"','",C10,"','",D10,",'",E10,"','",F10,"','",G10,"',",H10) -> 1009,'LICENCIATURA','MATERIAS INSTITUCIONALES','TC0201 4','CASILLAS MORA MONICA DANIELA','EXPERIENCIA DE ACCION SOCIAL','FEMENINO',1 | J10: =CONCATENATE($I$1,I10,");") -> INSERT INTO profesores (id,nivel,carrera,grupo,nombre,materia,sexo,sello) VALUES (1009,'LICENCIATURA','MATERIAS INSTITUCIONALES','TC0201 4','CASILLAS MORA MONICA DANIELA','EXPERIENCIA DE ACCION SOCIAL','FEMENINO',1);
A11: =A10+1 -> 1010 | B11: LICENCIATURA | C11: =Hoja1!B11 -> MATERIAS INSTITUCIONALES | D11: TC0201 5' | E11: =Hoja1!D11 -> HERNANDEZ MONTAÑO AIDA CITLALI | F11: =Hoja1!E11 -> EXPERIENCIA DE ACCION SOCIAL | G11: =Hoja1!F11 -> FEMENINO | H11: =IF(C11="MATERIAS INSTITUCIONALES",1,0) -> 1 | I11: =CONCATENATE(A11,",'",B11,"','",C11,"','",D11,",'",E11,"','",F11,"','",G11,"',",H11) -> 1010,'LICENCIATURA','MATERIAS INSTITUCIONALES','TC0201 5','HERNANDEZ MONTAÑO AIDA CITLALI','EXPERIENCIA DE ACCION SOCIAL','FEMENINO',1 | J11: =CONCATENATE($I$1,I11,");") -> INSERT INTO profesores (id,nivel,carrera,grupo,nombre,materia,sexo,sello) VALUES (1010,'LICENCIATURA','MATERIAS INSTITUCIONALES','TC0201 5','HERNANDEZ MONTAÑO AIDA CITLALI','EXPERIENCIA DE ACCION SOCIAL','FEMENINO',1);
A12: =A11+1 -> 1011 | B12: LICENCIATURA | C12: =Hoja1!B12 -> MATERIAS INSTITUCIONALES | D12: TC0201 6' | E12: =Hoja1!D12 -> AGUILAR CEBALLOS CARLA MARIANA | F12: =Hoja1!E12 -> EXPERIENCIA DE ACCION SOCIAL | G12: =Hoja1!F12 -> FEMENINO | H12: =IF(C12="MATERIAS INSTITUCIONALES",1,0) -> 1 | I12: =CONCATENATE(A12,",'",B12,"','",C12,"','",D12,",'",E12,"','",F12,"','",G12,"',",H12) -> 1011,'LICENCIATURA','MATERIAS INSTITUCIONALES','TC0201 6','AGUILAR CEBALLOS CARLA MARIANA','EXPERIENCIA DE ACCION SOCIAL','FEMENINO',1 | J12: =CONCATENATE($I$1,I12,");") -> INSERT INTO profesores (id,nivel,carrera,grupo,nombre,materia,sexo,sello) VALUES (1011,'LICENCIATURA','MATERIAS INSTITUCIONALES','TC0201 6','AGUILAR CEBALLOS CARLA MARIANA','EXPERIENCIA DE ACCION SOCIAL','FEMENINO',1);
A13: =A12+1 -> 1012 | B13: LICENCIATURA | C13: =Hoja1!B13 -> MATERIAS INSTITUCIONALES | D13: TC0201 7' | E13: =Hoja1!D13 -> FARIAS CASTELLANOS ISIS | F13: =Hoja1!E13 -> EXPERIENCIA DE ACCION SOCIAL | G13: =Hoja1!F13 -> FEMENINO | H13: =IF(C13="MATERIAS INSTITUCIONALES",1,0) -> 1 | I13: =CONCATENATE(A13,",'",B13,"','",C13,"','",D13,",'",E13,"','",F13,"','",G13,"',",H13) -> 1012,'LICENCIATURA','MATERIAS INSTITUCIONALES','TC0201 7','FARIAS CASTELLANOS ISIS','EXPERIENCIA DE ACCION SOCIAL','FEMENINO',1 | J13: =CONCATENATE($I$1,I13,");") -> INSERT INTO profesores (id,nivel,carrera,grupo,nombre,materia,sexo,sello) VALUES (1012,'LICENCIATURA','MATERIAS INSTITUCIONALES','TC0201 7','FARIAS CASTELLANOS ISIS','EXPERIENCIA DE ACCION SOCIAL','FEMENINO',1);
A14: =A13+1 -> 1013 | B14: LICENCIATURA | C14: =Hoja1!B14 -> MATERIAS INSTITUCIONALES | D14: TC0201 8' | E14: =Hoja1!D14 -> CASILLAS MORA MONICA DANIELA | F14: =Hoja1!E14 -> EXPERIENCIA DE ACCION SOCIAL | G14: =Hoja1!F14 -> FEMENINO | H14: =IF(C14="MATERIAS INSTITUCIONALES",1,0) -> 1 | I14: =CONCATENATE(A14,",'",B14,"','",C14,"','",D14,",'",E14,"','",F14,"','",G14,"',",H14) -> 1013,'LICENCIATURA','MATERIAS INSTITUCIONALES','TC0201 8','CASILLAS MORA MONICA DANIELA','EXPERIENCIA DE ACCION SOCIAL','FEMENINO',1 | J14: =CONCATENATE($I$1,I14,");") -> INSERT INTO profesores (id,nivel,carrera,grupo,nombre,materia,sexo,sello) VALUES (1013,'LICENCIATURA','MATERIAS INSTITUCIONALES','TC0201 8','CASILLAS MORA MONICA DANIELA','EXPERIENCIA DE ACCION SOCIAL','FEMENINO',1);
... A50: =A49+1 -> 1049 | B50: LICENCIATURA | C50: =Hoja1!B50 -> MATERIAS INSTITUCIONALES | D50: TC0801 5' | E50: =Hoja1!D50 -> BUSTAMANTE RAMIREZ LIDIA SELENE | F50: =Hoja1!E50 -> ESCENARIO DE INTERVENCION III | G50: =Hoja1!F50 -> MASCULINO | H50: =IF(C50="MATERIAS INSTITUCIONALES",1,0) -> 1 | I50: =CONCATENATE(A50,",'",B50,"','",C50,"','",D50,",'",E50,"','",F50,"','",G50,"',",H50) -> 1049,'LICENCIATURA','MATERIAS INSTITUCIONALES','TC0801 5','BUSTAMANTE RAMIREZ LIDIA SELENE','ESCENARIO DE INTERVENCION III','MASCULINO',1 | J50: =CONCATENATE($I$1,I50,");") -> INSERT INTO profesores (id,nivel,carrera,grupo,nombre,materia,sexo,sello) VALUES (1049,'LICENCIATURA','MATERIAS INSTITUCIONALES','TC0801 5','BUSTAMANTE RAMIREZ LIDIA SELENE','ESCENARIO DE INTERVENCION III','MASCULINO',1);
A51: =A50+1 -> 1050 | B51: LICENCIATURA | C51: IDIOMAS | D51: TIDIOMAS_1' | E51: =Hoja1!D51 -> ESPEJO REGALADO ERIKA | F51: =Hoja1!E51 -> IDIOMAS 2 | G51: =Hoja1!F51 -> FEMENINO | H51: 1 | I51: =CONCATENATE(A51,",'",B51,"','",C51,"','",D51,",'",E51,"','",F51,"','",G51,"',",H51) -> 1050,'LICENCIATURA','IDIOMAS','TIDIOMAS_1','ESPEJO REGALADO ERIKA','IDIOMAS 2','FEMENINO',1 | J51: =CONCATENATE($I$1,I51,");") -> INSERT INTO profesores (id,nivel,carrera,grupo,nombre,materia,sexo,sello) VALUES (1050,'LICENCIATURA','IDIOMAS','TIDIOMAS_1','ESPEJO REGALADO ERIKA','IDIOMAS 2','FEMENINO',1);
A52: =A51+1 -> 1051 | B52: LICENCIATURA | C52: IDIOMAS | D52: TIDIOMAS_2' | E52: =Hoja1!D52 -> CORTES VELASCO CLAUDIA PAOLA | F52: =Hoja1!E52 -> IDIOMAS 2 | G52: =Hoja1!F52 -> FEMENINO | H52: 1 | I52: =CONCATENATE(A52,",'",B52,"','",C52,"','",D52,",'",E52,"','",F52,"','",G52,"',",H52) -> 1051,'LICENCIATURA','IDIOMAS','TIDIOMAS_2','CORTES VELASCO CLAUDIA PAOLA','IDIOMAS 2','FEMENINO',1 | J52: =CONCATENATE($I$1,I52,");") -> INSERT INTO profesores (id,nivel,carrera,grupo,nombre,materia,sexo,sello) VALUES (1051,'LICENCIATURA','IDIOMAS','TIDIOMAS_2','CORTES VELASCO CLAUDIA PAOLA','IDIOMAS 2','FEMENINO',1);
A53: =A52+1 -> 1052 | B53: LICENCIATURA | C53: IDIOMAS | D53: TIDIOMAS_3' | E53: =Hoja1!D53 -> GARIBAY GARCIA GABRIELA | F53: =Hoja1!E53 -> IDIOMAS 2 | G53: =Hoja1!F53 -> FEMENINO | H53: 1 | I53: =CONCATENATE(A53,",'",B53,"','",C53,"','",D53,",'",E53,"','",F53,"','",G53,"',",H53) -> 1052,'LICENCIATURA','IDIOMAS','TIDIOMAS_3','GARIBAY GARCIA GABRIELA','IDIOMAS 2','FEMENINO',1 | J53: =CONCATENATE($I$1,I53,");") -> INSERT INTO profesores (id,nivel,carrera,grupo,nombre,materia,sexo,sello) VALUES (1052,'LICENCIATURA','IDIOMAS','TIDIOMAS_3','GARIBAY GARCIA GABRIELA','IDIOMAS 2','FEMENINO',1);
A54: =A53+1 -> 1053 | B54: LICENCIATURA | C54: IDIOMAS | D54: TIDIOMAS_4' | E54: =Hoja1!D54 -> DE LA ROSA RICARIO MELISSA | F54: =Hoja1!E54 -> IDIOMAS 2 | G54: =Hoja1!F54 -> FEMENINO | H54: 1 | I54: =CONCATENATE(A54,",'",B54,"','",C54,"','",D54,",'",E54,"','",F54,"','",G54,"',",H54) -> 1053,'LICENCIATURA','IDIOMAS','TIDIOMAS_4','DE LA ROSA RICARIO MELISSA','IDIOMAS 2','FEMENINO',1 | J54: =CONCATENATE($I$1,I54,");") -> INSERT INTO profesores (id,nivel,carrera,grupo,nombre,materia,sexo,sello) VALUES (1053,'LICENCIATURA','IDIOMAS','TIDIOMAS_4','DE LA ROSA RICARIO MELISSA','IDIOMAS 2','FEMENINO',1);
A55: =A54+1 -> 1054 | B55: LICENCIATURA | C55: IDIOMAS | D55: TIDIOMAS_5' | E55: =Hoja1!D55 -> MONCAYO TARIN ITZEL ALABAMA | F55: =Hoja1!E55 -> IDIOMAS 2 | G55: =Hoja1!F55 -> FEMENINO | H55: 1 | I55: =CONCATENATE(A55,",'",B55,"','",C55,"','",D55,",'",E55,"','",F55,"','",G55,"',",H55) -> 1054,'LICENCIATURA','IDIOMAS','TIDIOMAS_5','MONCAYO TARIN ITZEL ALABAMA','IDIOMAS 2','FEMENINO',1 | J55: =CONCATENATE($I$1,I55,");") -> INSERT INTO profesores (id,nivel,carrera,grupo,nombre,materia,sexo,sello) VALUES (1054,'LICENCIATURA','IDIOMAS','TIDIOMAS_5','MONCAYO TARIN ITZEL ALABAMA','IDIOMAS 2','FEMENINO',1);
A56: =A55+1 -> 1055 | B56: LICENCIATURA | C56: IDIOMAS | D56: TIDIOMAS_6' | E56: =Hoja1!D56 -> QUIROZ ZEPEDA JUAN PABLO | F56: =Hoja1!E56 -> IDIOMAS 2 | G56: =Hoja1!F56 -> MASCULINO | H56: 1 | I56: =CONCATENATE(A56,",'",B56,"','",C56,"','",D56,",'",E56,"','",F56,"','",G56,"',",H56) -> 1055,'LICENCIATURA','IDIOMAS','TIDIOMAS_6','QUIROZ ZEPEDA JUAN PABLO','IDIOMAS 2','MASCULINO',1 | J56: =CONCATENATE($I$1,I56,");") -> INSERT INTO profesores (id,nivel,carrera,grupo,nombre,materia,sexo,sello) VALUES (1055,'LICENCIATURA','IDIOMAS','TIDIOMAS_6','QUIROZ ZEPEDA JUAN PABLO','IDIOMAS 2','MASCULINO',1);
A57: =A56+1 -> 1056 | B57: LICENCIATURA | C57: IDIOMAS | D57: TIDIOMAS_7' | E57: =Hoja1!D57 -> JIMENEZ ROBLES LINA ADITH | F57: =Hoja1!E57 -> IDIOMAS 2 | G57: =Hoja1!F57 -> FEMENINO | H57: 1 | I57: =CONCATENATE(A57,",'",B57,"','",C57,"','",D57,",'",E57,"','",F57,"','",G57,"',",H57) -> 1056,'LICENCIATURA','IDIOMAS','TIDIOMAS_7','JIMENEZ ROBLES LINA ADITH','IDIOMAS 2','FEMENINO',1 | J57: =CONCATENATE($I$1,I57,");") -> INSERT INTO profesores (id,nivel,carrera,grupo,nombre,materia,sexo,sello) VALUES (1056,'LICENCIATURA','IDIOMAS','TIDIOMAS_7','JIMENEZ ROBLES LINA ADITH','IDIOMAS 2','FEMENINO',1);
A58: =A57+1 -> 1057 | B58: LICENCIATURA | C58: =Hoja1!B58 -> ADMINISTRACION Y DIRECCION DE NEGOCIOS | D58: ADMON 2°' | E58: =Hoja1!D58 -> DELGADO BEJAR RUTH | F58: =Hoja1!E58 -> CONTABILIDAD BASICA | G58: =Hoja1!F58 -> FEMENINO | H58: =IF(C58="MATERIAS INSTITUCIONALES",1,0) -> 0 | I58: =CONCATENATE(A58,",'",B58,"','",C58,"','",D58,",'",E58,"','",F58,"','",G58,"',",H58) -> 1057,'LICENCIATURA','ADMINISTRACION Y DIRECCION DE NEGOCIOS','ADMON 2°','DELGADO BEJAR RUTH','CONTABILIDAD BASICA','FEMENINO',0 | J58: =CONCATENATE($I$1,I58,");") -> INSERT INTO profesores (id,nivel,carrera,grupo,nombre,materia,sexo,sello) VALUES (1057,'LICENCIATURA','ADMINISTRACION Y DIRECCION DE NEGOCIOS','ADMON 2°','DELGADO BEJAR RUTH','CONTABILIDAD BASICA','FEMENINO',0);
A59: =A58+1 -> 1058 | B59: LICENCIATURA | C59: =Hoja1!B59 -> ADMINISTRACION Y DIRECCION DE NEGOCIOS | D59: ADMON 2°' | E59: =Hoja1!D59 -> ESCARCEGA GARCIA DE LEON MIGUEL ANGEL | F59: =Hoja1!E59 -> ESTADISTICA I | G59: =Hoja1!F59 -> MASCULINO | H59: =IF(C59="MATERIAS INSTITUCIONALES",1,0) -> 0 | I59: =CONCATENATE(A59,",'",B59,"','",C59,"','",D59,",'",E59,"','",F59,"','",G59,"',",H59) -> 1058,'LICENCIATURA','ADMINISTRACION Y DIRECCION DE NEGOCIOS','ADMON 2°','ESCARCEGA GARCIA DE LEON MIGUEL ANGEL','ESTADISTICA I','MASCULINO',0 | J59: =CONCATENATE($I$1,I59,");") -> INSERT INTO profesores (id,nivel,carrera,grupo,nombre,materia,sexo,sello) VALUES (1058,'LICENCIATURA','ADMINISTRACION Y DIRECCION DE NEGOCIOS','ADMON 2°','ESCARCEGA GARCIA DE LEON MIGUEL ANGEL','ESTADISTICA I','MASCULINO',0);
A60: =A59+1 -> 1059 | B60: LICENCIATURA | C60: =Hoja1!B60 -> ADMINISTRACION Y DIRECCION DE NEGOCIOS | D60: ADMON 2°' | E60: =Hoja1!D60 -> LUA HERRERA LILIANA | F60: =Hoja1!E60 -> MATEMATICAS FINANCIERAS | G60: =Hoja1!F60 -> FEMENINO | H60: =IF(C60="MATERIAS INSTITUCIONALES",1,0) -> 0 | I60: =CONCATENATE(A60,",'",B60,"','",C60,"','",D60,",'",E60,"','",F60,"','",G60,"',",H60) -> 1059,'LICENCIATURA','ADMINISTRACION Y DIRECCION DE NEGOCIOS','ADMON 2°','LUA HERRERA LILIANA','MATEMATICAS FINANCIERAS','FEMENINO',0 | J60: =CONCATENATE($I$1,I60,");") -> INSERT INTO profesores (id,nivel,carrera,grupo,nombre,materia,sexo,sello) VALUES (1059,'LICENCIATURA','ADMINISTRACION Y DIRECCION DE NEGOCIOS','ADMON 2°','LUA HERRERA LILIANA','MATEMATICAS FINANCIERAS','FEMENINO',0);
A61: =A60+1 -> 1060 | B61: LICENCIATURA | C61: =Hoja1!B61 -> ADMINISTRACION Y DIRECCION DE NEGOCIOS | D61: ADMON 2°' | E61: =Hoja1!D61 -> MORENO CORRAL ALVARO | F61: =Hoja1!E61 -> PLANEACION ESTRATEGICA | G61: =Hoja1!F61 -> MASCULINO | H61: =IF(C61="MATERIAS INSTITUCIONALES",1,0) -> 0 | I61: =CONCATENATE(A61,",'",B61,"','",C61,"','",D61,",'",E61,"','",F61,"','",G61,"',",H61) -> 1060,'LICENCIATURA','ADMINISTRACION Y DIRECCION DE NEGOCIOS','ADMON 2°','MORENO CORRAL ALVARO','PLANEACION ESTRATEGICA','MASCULINO',0 | J61: =CONCATENATE($I$1,I61,");") -> INSERT INTO profesores (id,nivel,carrera,grupo,nombre,materia,sexo,sello) VALUES (1060,'LICENCIATURA','ADMINISTRACION Y DIRECCION DE NEGOCIOS','ADMON 2°','MORENO CORRAL ALVARO','PLANEACION ESTRATEGICA','MASCULINO',0);
A62: =A61+1 -> 1061 | B62: LICENCIATURA | C62: =Hoja1!B62 -> ADMINISTRACION Y DIRECCION DE NEGOCIOS | D62: ADMON 2°' | E62: =Hoja1!D62 -> OROZCO DIAZ BEATRIZ IRENE | F62: =Hoja1!E62 -> DERECHO MERCANTIL | G62: =Hoja1!F62 -> FEMENINO | H62: =IF(C62="MATERIAS INSTITUCIONALES",1,0) -> 0 | I62: =CONCATENATE(A62,",'",B62,"','",C62,"','",D62,",'",E62,"','",F62,"','",G62,"',",H62) -> 1061,'LICENCIATURA','ADMINISTRACION Y DIRECCION DE NEGOCIOS','ADMON 2°','OROZCO DIAZ BEATRIZ IRENE','DERECHO MERCANTIL','FEMENINO',0 | J62: =CONCATENATE($I$1,I62,");") -> INSERT INTO profesores (id,nivel,carrera,grupo,nombre,materia,sexo,sello) VALUES (1061,'LICENCIATURA','ADMINISTRACION Y DIRECCION DE NEGOCIOS','ADMON 2°','OROZCO DIAZ BEATRIZ IRENE','DERECHO MERCANTIL','FEMENINO',0);
A63: =A62+1 -> 1062 | B63: LICENCIATURA | C63: =Hoja1!B63 -> ADMINISTRACION Y DIRECCION DE NEGOCIOS | D63: ADMON 2°' | E63: =Hoja1!D63 -> PADILLA MARTINEZ ELSA GEORGINA | F63: =Hoja1!E63 -> DISEÑO DE ESTRUCTURAS Y SISTEMAS ADMINISTRATIVOS | G63: =Hoja1!F63 -> FEMENINO | H63: =IF(C63="MATERIAS INSTITUCIONALES",1,0) -> 0 | I63: =CONCATENATE(A63,",'",B63,"','",C63,"','",D63,",'",E63,"','",F63,"','",G63,"',",H63) -> 1062,'LICENCIATURA','ADMINISTRACION Y DIRECCION DE NEGOCIOS','ADMON 2°','PADILLA MARTINEZ ELSA GEORGINA','DISEÑO DE ESTRUCTURAS Y SISTEMAS ADMINISTRATIVOS','FEMENINO',0 | J63: =CONCATENATE($I$1,I63,");") -> INSERT INTO profesores (id,nivel,carrera,grupo,nombre,materia,sexo,sello) VALUES (1062,'LICENCIATURA','ADMINISTRACION Y DIRECCION DE NEGOCIOS','ADMON 2°','PADILLA MARTINEZ ELSA GEORGINA','DISEÑO DE ESTRUCTURAS Y SISTEMAS ADMINISTRATIVOS','FEMENINO',0);
A64: =A63+1 -> 1063 | B64: LICENCIATURA | C64: =Hoja1!B64 -> ADMINISTRACION Y DIRECCION DE NEGOCIOS | D64: ADMON 2°' | E64: =Hoja1!D64 -> RODRIGUEZ ROMERO DENIS PAUL | F64: =Hoja1!E64 -> ECONOMIA MEXICANA Y DESARROLLO | G64: =Hoja1!F64 -> MASCULINO | H64: =IF(C64="MATERIAS INSTITUCIONALES",1,0) -> 0 | I64: =CONCATENATE(A64,",'",B64,"','",C64,"','",D64,",'",E64,"','",F64,"','",G64,"',",H64) -> 1063,'LICENCIATURA','ADMINISTRACION Y DIRECCION DE NEGOCIOS','ADMON 2°','RODRIGUEZ ROMERO DENIS PAUL','ECONOMIA MEXICANA Y DESARROLLO','MASCULINO',0 | J64: =CONCATENATE($I$1,I64,");") -> INSERT INTO profesores (id,nivel,carrera,grupo,nombre,materia,sexo,sello) VALUES (1063,'LICENCIATURA','ADMINISTRACION Y DIRECCION DE NEGOCIOS','ADMON 2°','RODRIGUEZ ROMERO DENIS PAUL','ECONOMIA MEXICANA Y DESARROLLO','MASCULINO',0);
A65: =A64+1 -> 1064 | B65: LICENCIATURA | C65: =Hoja1!B65 -> ADMINISTRACION Y DIRECCION DE NEGOCIOS | D65: ADMON 4°' | E65: =Hoja1!D65 -> ESCARCEGA GARCIA DE LEON MIGUEL ANGEL | F65: =Hoja1!E65 -> FUNDAMENTOS DE MERCADOTECNIA | G65: =Hoja1!F65 -> MASCULINO | H65: =IF(C65="MATERIAS INSTITUCIONALES",1,0) -> 0 | I65: =CONCATENATE(A65,",'",B65,"','",C65,"','",D65,",'",E65,"','",F65,"','",G65,"',",H65) -> 1064,'LICENCIATURA','ADMINISTRACION Y DIRECCION DE NEGOCIOS','ADMON 4°','ESCARCEGA GARCIA DE LEON MIGUEL ANGEL','FUNDAMENTOS DE MERCADOTECNIA','MASCULINO',0 | J65: =CONCATENATE($I$1,I65,");") -> INSERT INTO profesores (id,nivel,carrera,grupo,nombre,materia,sexo,sello) VALUES (1064,'LICENCIATURA','ADMINISTRACION Y DIRECCION DE NEGOCIOS','ADMON 4°','ESCARCEGA GARCIA DE LEON MIGUEL ANGEL','FUNDAMENTOS DE MERCADOTECNIA','MASCULINO',0);
A66: =A65+1 -> 1065 | B66: LICENCIATURA | C66: =Hoja1!B66 -> ADMINISTRACION Y DIRECCION DE NEGOCIOS | D66: ADMON 4°' | E66: =Hoja1!D66 -> GUILLEN LAGUNES JOSE JAVIER | F66: =Hoja1!E66 -> DIAGNOSTICO Y DESARROLLO ORGANIZACIONAL | G66: =Hoja1!F66 -> MASCULINO | H66: =IF(C66="MATERIAS INSTITUCIONALES",1,0) -> 0 | I66: =CONCATENATE(A66,",'",B66,"','",C66,"','",D66,",'",E66,"','",F66,"','",G66,"',",H66) -> 1065,'LICENCIATURA','ADMINISTRACION Y DIRECCION DE NEGOCIOS','ADMON 4°','GUILLEN LAGUNES JOSE JAVIER','DIAGNOSTICO Y DESARROLLO ORGANIZACIONAL','MASCULINO',0 | J66: =CONCATENATE($I$1,I66,");") -> INSERT INTO profesores (id,nivel,carrera,grupo,nombre,materia,sexo,sello) VALUES (1065,'LICENCIATURA','ADMINISTRACION Y DIRECCION DE NEGOCIOS','ADMON 4°','GUILLEN LAGUNES JOSE JAVIER','DIAGNOSTICO Y DESARROLLO ORGANIZACIONAL','MASCULINO',0);
A67: =A66+1 -> 1066 | B67: LICENCIATURA | C67: =Hoja1!B67 -> ADMINISTRACION Y DIRECCION DE NEGOCIOS | D67: ADMON 4°' | E67: =Hoja1!D67 -> LUA HERRERA LILIANA | F67: =Hoja1!E67 -> DERECHO TRIBUTARIO | G67: =Hoja1!F67 -> FEMENINO | H67: =IF(C67="MATERIAS INSTITUCIONALES",1,0) -> 0 | I67: =CONCATENATE(A67,",'",B67,"','",C67,"','",D67,",'",E67,"','",F67,"','",G67,"',",H67) -> 1066,'LICENCIATURA','ADMINISTRACION Y DIRECCION DE NEGOCIOS','ADMON 4°','LUA HERRERA LILIANA','DERECHO TRIBUTARIO','FEMENINO',0 | J67: =CONCATENATE($I$1,I67,");") -> INSERT INTO profesores (id,nivel,carrera,grupo,nombre,materia,sexo,sello) VALUES (1066,'LICENCIATURA','ADMINISTRACION Y DIRECCION DE NEGOCIOS','ADMON 4°','LUA HERRERA LILIANA','DERECHO TRIBUTARIO','FEMENINO',0);
A68: =A67+1 -> 1067 | B68: LICENCIATURA | C68: =Hoja1!B68 -> ADMINISTRACION Y DIRECCION DE NEGOCIOS | D68: ADMON 4°' | E68: =Hoja1!D68 -> MAGALLON RAMIREZ MARIA DEL CARMEN | F68: =Hoja1!E68 -> GESTIÓN FINANCIERA | G68: =Hoja1!F68 -> FEMENINO | H68: =IF(C68="MATERIAS INSTITUCIONALES",1,0) -> 0 | I68: =CONCATENATE(A68,",'",B68,"','",C68,"','",D68,",'",E68,"','",F68,"','",G68,"',",H68) -> 1067,'LICENCIATURA','ADMINISTRACION Y DIRECCION DE NEGOCIOS','ADMON 4°','MAGALLON RAMIREZ MARIA DEL CARMEN','GESTIÓN FINANCIERA','FEMENINO',0 | J68: =CONCATENATE($I$1,I68,");") -> INSERT INTO profesores (id,nivel,carrera,grupo,nombre,materia,sexo,sello) VALUES (1067,'LICENCIATURA','ADMINISTRACION Y DIRECCION DE NEGOCIOS','ADMON 4°','MAGALLON RAMIREZ MARIA DEL CARMEN','GESTIÓN FINANCIERA','FEMENINO',0);
A69: =A68+1 -> 1068 | B69: LICENCIATURA | C69: =Hoja1!B69 -> ADMINISTRACION Y DIRECCION DE NEGOCIOS | D69: ADMON 4°' | E69: =Hoja1!D69 -> RODRIGUEZ ROMERO DENIS PAUL | F69: =Hoja1!E69 -> PRESUPUESTOS | G69: =Hoja1!F69 -> MASCULINO | H69: =IF(C69="MATERIAS INSTITUCIONALES",1,0) -> 0 | I69: =CONCATENATE(A69,",'",B69,"','",C69,"','",D69,",'",E69,"','",F69,"','",G69,"',",H69) -> 1068,'LICENCIATURA','ADMINISTRACION Y DIRECCION DE NEGOCIOS','ADMON 4°','RODRIGUEZ ROMERO DENIS PAUL','PRESUPUESTOS','MASCULINO',0 | J69: =CONCATENATE($I$1,I69,");") -> INSERT INTO profesores (id,nivel,carrera,grupo,nombre,materia,sexo,sello) VALUES (1068,'LICENCIATURA','ADMINISTRACION Y DIRECCION DE NEGOCIOS','ADMON 4°','RODRIGUEZ ROMERO DENIS PAUL','PRESUPUESTOS','MASCULINO',0);
... A118: =A117+1 -> 1117 | B118: LICENCIATURA | C118: =Hoja1!B118 -> ARQUITECTURA | D118: ARQ 2°' | E118: =Hoja1!D118 -> PUJOL BECERRA ALVARO | F118: =Hoja1!E118 -> DIBUJO ASISTIDO POR COMPUTADORA | G118: =Hoja1!F118 -> MASCULINO | H118: =IF(C118="MATERIAS INSTITUCIONALES",1,0) -> 0 | I118: =CONCATENATE(A118,",'",B118,"','",C118,"','",D118,",'",E118,"','",F118,"','",G118,"',",H118) -> 1117,'LICENCIATURA','ARQUITECTURA','ARQ 2°','PUJOL BECERRA ALVARO','DIBUJO ASISTIDO POR COMPUTADORA','MASCULINO',0 | J118: =CONCATENATE($I$1,I118,");") -> INSERT INTO profesores (id,nivel,carrera,grupo,nombre,materia,sexo,sello) VALUES (1117,'LICENCIATURA','ARQUITECTURA','ARQ 2°','PUJOL BECERRA ALVARO','DIBUJO ASISTIDO POR COMPUTADORA','MASCULINO',0);
A119: =A118+1 -> 1118 | B119: LICENCIATURA | C119: =Hoja1!B119 -> ARQUITECTURA | D119: ARQ 4°' | E119: CUESTA SÁNCHEZ EDUARDO | F119: =Hoja1!E119 -> HISTORIA DE LA ARQUITECTURA MEXICANA | G119: =Hoja1!F119 -> MASCULINO | H119: =IF(C119="MATERIAS INSTITUCIONALES",1,0) -> 0 | I119: =CONCATENATE(A119,",'",B119,"','",C119,"','",D119,",'",E119,"','",F119,"','",G119,"',",H119) -> 1118,'LICENCIATURA','ARQUITECTURA','ARQ 4°','CUESTA SÁNCHEZ EDUARDO','HISTORIA DE LA ARQUITECTURA MEXICANA','MASCULINO',0 | J119: =CONCATENATE($I$1,I119,");") -> INSERT INTO profesores (id,nivel,carrera,grupo,nombre,materia,sexo,sello) VALUES (1118,'LICENCIATURA','ARQUITECTURA','ARQ 4°','CUESTA SÁNCHEZ EDUARDO','HISTORIA DE LA ARQUITECTURA MEXICANA','MASCULINO',0);
A120: =A119+1 -> 1119 | B120: LICENCIATURA | C120: =Hoja1!B120 -> ARQUITECTURA | D120: ARQ 4°' | E120: =Hoja1!D120 -> ESPINO CAMPOS NYDIA | F120: =Hoja1!E120 -> DISEÑO DEL ESPACIO RELIGIOSO Y EDUCATIVO | G120: =Hoja1!F120 -> FEMENINO | H120: =IF(C120="MATERIAS INSTITUCIONALES",1,0) -> 0 | I120: =CONCATENATE(A120,",'",B120,"','",C120,"','",D120,",'",E120,"','",F120,"','",G120,"',",H120) -> 1119,'LICENCIATURA','ARQUITECTURA','ARQ 4°','ESPINO CAMPOS NYDIA','DISEÑO DEL ESPACIO RELIGIOSO Y EDUCATIVO','FEMENINO',0 | J120: =CONCATENATE($I$1,I120,");") -> INSERT INTO profesores (id,nivel,carrera,grupo,nombre,materia,sexo,sello) VALUES (1119,'LICENCIATURA','ARQUITECTURA','ARQ 4°','ESPINO CAMPOS NYDIA','DISEÑO DEL ESPACIO RELIGIOSO Y EDUCATIVO','FEMENINO',0);
A121: =A120+1 -> 1120 | B121: LICENCIATURA | C121: =Hoja1!B121 -> ARQUITECTURA | D121: ARQ 4°' | E121: =Hoja1!D121 -> MARTINEZ GOMEZ LETICIA | F121: =Hoja1!E121 -> ARQUITECTURA DEL PAISAJISMO | G121: =Hoja1!F121 -> FEMENINO | H121: =IF(C121="MATERIAS INSTITUCIONALES",1,0) -> 0 | I121: =CONCATENATE(A121,",'",B121,"','",C121,"','",D121,",'",E121,"','",F121,"','",G121,"',",H121) -> 1120,'LICENCIATURA','ARQUITECTURA','ARQ 4°','MARTINEZ GOMEZ LETICIA','ARQUITECTURA DEL PAISAJISMO','FEMENINO',0 | J121: =CONCATENATE($I$1,I121,");") -> INSERT INTO profesores (id,nivel,carrera,grupo,nombre,materia,sexo,sello) VALUES (1120,'LICENCIATURA','ARQUITECTURA','ARQ 4°','MARTINEZ GOMEZ LETICIA','ARQUITECTURA DEL PAISAJISMO','FEMENINO',0);
A122: =A121+1 -> 1121 | B122: LICENCIATURA | C122: =Hoja1!B122 -> ARQUITECTURA | D122: ARQ 4°' | E122: =Hoja1!D122 -> MONTELONGO AGUAYO DANIEL | F122: =Hoja1!E122 -> DISEÑO DE INSTALACIONES HIDRAULICAS SANITARIAS | G122: =Hoja1!F122 -> MASCULINO | H122: =IF(C122="MATERIAS INSTITUCIONALES",1,0) -> 0 | I122: =CONCATENATE(A122,",'",B122,"','",C122,"','",D122,",'",E122,"','",F122,"','",G122,"',",H122) -> 1121,'LICENCIATURA','ARQUITECTURA','ARQ 4°','MONTELONGO AGUAYO DANIEL','DISEÑO DE INSTALACIONES HIDRAULICAS SANITARIAS','MASCULINO',0 | J122: =CONCATENATE($I$1,I122,");") -> INSERT INTO profesores (id,nivel,carrera,grupo,nombre,materia,sexo,sello) VALUES (1121,'LICENCIATURA','ARQUITECTURA','ARQ 4°','MONTELONGO AGUAYO DANIEL','DISEÑO DE INSTALACIONES HIDRAULICAS SANITARIAS','MASCULINO',0);
A123: =A122+1 -> 1122 | B123: LICENCIATURA | C123: =Hoja1!B123 -> ARQUITECTURA | D123: ARQ 4°' | E123: =Hoja1!D123 -> RAMOS RENTERIA MONTSERRAT FABIOLA | F123: =Hoja1!E123 -> FOTOGRAFIA | G123: =Hoja1!F123 -> FEMENINO | H123: =IF(C123="MATERIAS INSTITUCIONALES",1,0) -> 0 | I123: =CONCATENATE(A123,",'",B123,"','",C123,"','",D123,",'",E123,"','",F123,"','",G123,"',",H123) -> 1122,'LICENCIATURA','ARQUITECTURA','ARQ 4°','RAMOS RENTERIA MONTSERRAT FABIOLA','FOTOGRAFIA','FEMENINO',0 | J123: =CONCATENATE($I$1,I123,");") -> INSERT INTO profesores (id,nivel,carrera,grupo,nombre,materia,sexo,sello) VALUES (1122,'LICENCIATURA','ARQUITECTURA','ARQ 4°','RAMOS RENTERIA MONTSERRAT FABIOLA','FOTOGRAFIA','FEMENINO',0);
A124: =A123+1 -> 1123 | B124: LICENCIATURA | C124: =Hoja1!B124 -> ARQUITECTURA | D124: ARQ 4°' | E124: =Hoja1!D124 -> SANCHEZ MUÑOZ JOSE JORGE | F124: =Hoja1!E124 -> HISTORIA CRITICA DEL URBANISMO | G124: =Hoja1!F124 -> MASCULINO | H124: =IF(C124="MATERIAS INSTITUCIONALES",1,0) -> 0 | I124: =CONCATENATE(A124,",'",B124,"','",C124,"','",D124,",'",E124,"','",F124,"','",G124,"',",H124) -> 1123,'LICENCIATURA','ARQUITECTURA','ARQ 4°','SANCHEZ MUÑOZ JOSE JORGE','HISTORIA CRITICA DEL URBANISMO','MASCULINO',0 | J124: =CONCATENATE($I$1,I124,");") -> INSERT INTO profesores (id,nivel,carrera,grupo,nombre,materia,sexo,sello) VALUES (1123,'LICENCIATURA','ARQUITECTURA','ARQ 4°','SANCHEZ MUÑOZ JOSE JORGE','HISTORIA CRITICA DEL URBANISMO','MASCULINO',0);
A125: =A124+1 -> 1124 | B125: LICENCIATURA | C125: =Hoja1!B125 -> ARQUITECTURA | D125: ARQ 4°' | E125: =Hoja1!D125 -> SEGOVIANO MARTINEZ HUGO MIGUEL | F125: =Hoja1!E125 -> DISEÑO DE ESTRUCTURAS DE ACERO | G125: =Hoja1!F125 -> MASCULINO | H125: =IF(C125="MATERIAS INSTITUCIONALES",1,0) -> 0 | I125: =CONCATENATE(A125,",'",B125,"','",C125,"','",D125,",'",E125,"','",F125,"','",G125,"',",H125) -> 1124,'LICENCIATURA','ARQUITECTURA','ARQ 4°','SEGOVIANO MARTINEZ HUGO MIGUEL','DISEÑO DE ESTRUCTURAS DE ACERO','MASCULINO',0 | J125: =CONCATENATE($I$1,I125,");") -> INSERT INTO profesores (id,nivel,carrera,grupo,nombre,materia,sexo,sello) VALUES (1124,'LICENCIATURA','ARQUITECTURA','ARQ 4°','SEGOVIANO MARTINEZ HUGO MIGUEL','DISEÑO DE ESTRUCTURAS DE ACERO','MASCULINO',0);
A126: =A125+1 -> 1125 | B126: LICENCIATURA | C126: =Hoja1!B126 -> ARQUITECTURA | D126: ARQ 6°' | E126: CALDERON CHAVARRIN NOEMI MONTSERRAT | F126: =Hoja1!E126 -> CONSERVACION DEL PATRIMONIO CULTURAL | G126: =Hoja1!F126 -> MASCULINO | H126: =IF(C126="MATERIAS INSTITUCIONALES",1,0) -> 0 | I126: =CONCATENATE(A126,",'",B126,"','",C126,"','",D126,",'",E126,"','",F126,"','",G126,"',",H126) -> 1125,'LICENCIATURA','ARQUITECTURA','ARQ 6°','CALDERON CHAVARRIN NOEMI MONTSERRAT','CONSERVACION DEL PATRIMONIO CULTURAL','MASCULINO',0 | J126: =CONCATENATE($I$1,I126,");") -> INSERT INTO profesores (id,nivel,carrera,grupo,nombre,materia,sexo,sello) VALUES (1125,'LICENCIATURA','ARQUITECTURA','ARQ 6°','CALDERON CHAVARRIN NOEMI MONTSERRAT','CONSERVACION DEL PATRIMONIO CULTURAL','MASCULINO',0);
A127: =A126+1 -> 1126 | B127: LICENCIATURA | C127: =Hoja1!B127 -> ARQUITECTURA | D127: ARQ 6°' | E127: =Hoja1!D127 -> CASTELLANOS MEZA IRMA ELIZABETH | F127: =Hoja1!E127 -> ARQUITECTURA INTELIGENTE | G127: =Hoja1!F127 -> FEMENINO | H127: =IF(C127="MATERIAS INSTITUCIONALES",1,0) -> 0 | I127: =CONCATENATE(A127,",'",B127,"','",C127,"','",D127,",'",E127,"','",F127,"','",G127,"',",H127) -> 1126,'LICENCIATURA','ARQUITECTURA','ARQ 6°','CASTELLANOS MEZA IRMA ELIZABETH','ARQUITECTURA INTELIGENTE','FEMENINO',0 | J127: =CONCATENATE($I$1,I127,");") -> INSERT INTO profesores (id,nivel,carrera,grupo,nombre,materia,sexo,sello) VALUES (1126,'LICENCIATURA','ARQUITECTURA','ARQ 6°','CASTELLANOS MEZA IRMA ELIZABETH','ARQUITECTURA INTELIGENTE','FEMENINO',0);
A128: =A127+1 -> 1127 | B128: LICENCIATURA | C128: =Hoja1!B128 -> ARQUITECTURA | D128: ARQ 6°' | E128: =Hoja1!D128 -> FLORES COSIO LEONARDO | F128: =Hoja1!E128 -> DISEÑO ASISTIDO POR COMPUTADORA AVANZADO | G128: =Hoja1!F128 -> MASCULINO | H128: =IF(C128="MATERIAS INSTITUCIONALES",1,0) -> 0 | I128: =CONCATENATE(A128,",'",B128,"','",C128,"','",D128,",'",E128,"','",F128,"','",G128,"',",H128) -> 1127,'LICENCIATURA','ARQUITECTURA','ARQ 6°','FLORES COSIO LEONARDO','DISEÑO ASISTIDO POR COMPUTADORA AVANZADO','MASCULINO',0 | J128: =CONCATENATE($I$1,I128,");") -> INSERT INTO profesores (id,nivel,carrera,grupo,nombre,materia,sexo,sello) VALUES (1127,'LICENCIATURA','ARQUITECTURA','ARQ 6°','FLORES COSIO LEONARDO','DISEÑO ASISTIDO POR COMPUTADORA AVANZADO','MASCULINO',0);
A129: =A128+1 -> 1128 | B129: LICENCIATURA | C129: =Hoja1!B129 -> ARQUITECTURA | D129: ARQ 6°' | E129: =Hoja1!D129 -> PEREZ GUTIERREZ JORGE HUMBERTO | F129: =Hoja1!E129 -> RESCATE DE ZONAS URBANAS | G129: =Hoja1!F129 -> MASCULINO | H129: =IF(C129="MATERIAS INSTITUCIONALES",1,0) -> 0 | I129: =CONCATENATE(A129,",'",B129,"','",C129,"','",D129,",'",E129,"','",F129,"','",G129,"',",H129) -> 1128,'LICENCIATURA','ARQUITECTURA','ARQ 6°','PEREZ GUTIERREZ JORGE HUMBERTO','RESCATE DE ZONAS URBANAS','MASCULINO',0 | J129: =CONCATENATE($I$1,I129,");") -> INSERT INTO profesores (id,nivel,carrera,grupo,nombre,materia,sexo,sello) VALUES (1128,'LICENCIATURA','ARQUITECTURA','ARQ 6°','PEREZ GUTIERREZ JORGE HUMBERTO','RESCATE DE ZONAS URBANAS','MASCULINO',0);
A130: =A129+1 -> 1129 | B130: LICENCIATURA | C130: =Hoja1!B130 -> ARQUITECTURA | D130: ARQ 6°' | E130: =Hoja1!D130 -> PONCE CUEVAS JUAN | F130: =Hoja1!E130 -> COSTOS Y PRESUPUESTOS DE LA EDIFICACION | G130: =Hoja1!F130 -> MASCULINO | H130: =IF(C130="MATERIAS INSTITUCIONALES",1,0) -> 0 | I130: =CONCATENATE(A130,",'",B130,"','",C130,"','",D130,",'",E130,"','",F130,"','",G130,"',",H130) -> 1129,'LICENCIATURA','ARQUITECTURA','ARQ 6°','PONCE CUEVAS JUAN','COSTOS Y PRESUPUESTOS DE LA EDIFICACION','MASCULINO',0 | J130: =CONCATENATE($I$1,I130,");") -> INSERT INTO profesores (id,nivel,carrera,grupo,nombre,materia,sexo,sello) VALUES (1129,'LICENCIATURA','ARQUITECTURA','ARQ 6°','PONCE CUEVAS JUAN','COSTOS Y PRESUPUESTOS DE LA EDIFICACION','MASCULINO',0);
A131: =A130+1 -> 1130 | B131: LICENCIATURA | C131: =Hoja1!B131 -> ARQUITECTURA | D131: ARQ 6°' | E131: =Hoja1!D131 -> SANCHEZ MUÑOZ JOSE JORGE | F131: =Hoja1!E131 -> DISEÑO DEL ESPACIO CULTURAL Y RECREATIVO | G131: =Hoja1!F131 -> MASCULINO | H131: =IF(C131="MATERIAS INSTITUCIONALES",1,0) -> 0 | I131: =CONCATENATE(A131,",'",B131,"','",C131,"','",D131,",'",E131,"','",F131,"','",G131,"',",H131) -> 1130,'LICENCIATURA','ARQUITECTURA','ARQ 6°','SANCHEZ MUÑOZ JOSE JORGE','DISEÑO DEL ESPACIO CULTURAL Y RECREATIVO','MASCULINO',0 | J131: =CONCATENATE($I$1,I131,");") -> INSERT INTO profesores (id,nivel,carrera,grupo,nombre,materia,sexo,sello) VALUES (1130,'LICENCIATURA','ARQUITECTURA','ARQ 6°','SANCHEZ MUÑOZ JOSE JORGE','DISEÑO DEL ESPACIO CULTURAL Y RECREATIVO','MASCULINO',0);
A132: =A131+1 -> 1131 | B132: LICENCIATURA | C132: =Hoja1!B132 -> ARQUITECTURA | D132: ARQ 6°' | E132: =Hoja1!D132 -> SEGOVIANO MARTINEZ HUGO MIGUEL | F132: =Hoja1!E132 -> CIMENTACIONES Y TIPOS DE FALLAS | G132: =Hoja1!F132 -> MASCULINO | H132: =IF(C132="MATERIAS INSTITUCIONALES",1,0) -> 0 | I132: =CONCATENATE(A132,",'",B132,"','",C132,"','",D132,",'",E132,"','",F132,"','",G132,"',",H132) -> 1131,'LICENCIATURA','ARQUITECTURA','ARQ 6°','SEGOVIANO MARTINEZ HUGO MIGUEL','CIMENTACIONES Y TIPOS DE FALLAS','MASCULINO',0 | J132: =CONCATENATE($I$1,I132,");") -> INSERT INTO profesores (id,nivel,carrera,grupo,nombre,materia,sexo,sello) VALUES (1131,'LICENCIATURA','ARQUITECTURA','ARQ 6°','SEGOVIANO MARTINEZ HUGO MIGUEL','CIMENTACIONES Y TIPOS DE FALLAS','MASCULINO',0);
A133: =A132+1 -> 1132 | B133: LICENCIATURA | C133: =Hoja1!B133 -> ARQUITECTURA | D133: ARQ 8°' | E133: =Hoja1!D133 -> CASTELLANOS MEZA IRMA ELIZABETH | F133: =Hoja1!E133 -> DISEÑO ARQUITECTONICO SUSTENTABLE | G133: =Hoja1!F133 -> FEMENINO | H133: =IF(C133="MATERIAS INSTITUCIONALES",1,0) -> 0 | I133: =CONCATENATE(A133,",'",B133,"','",C133,"','",D133,",'",E133,"','",F133,"','",G133,"',",H133) -> 1132,'LICENCIATURA','ARQUITECTURA','ARQ 8°','CASTELLANOS MEZA IRMA ELIZABETH','DISEÑO ARQUITECTONICO SUSTENTABLE','FEMENINO',0 | J133: =CONCATENATE($I$1,I133,");") -> INSERT INTO profesores (id,nivel,carrera,grupo,nombre,materia,sexo,sello) VALUES (1132,'LICENCIATURA','ARQUITECTURA','ARQ 8°','CASTELLANOS MEZA IRMA ELIZABETH','DISEÑO ARQUITECTONICO SUSTENTABLE','FEMENINO',0);
A134: =A133+1 -> 1133 | B134: LICENCIATURA | C134: =Hoja1!B134 -> ARQUITECTURA | D134: ARQ 8°' | E134: =Hoja1!D134 -> ESPINO CAMPOS NYDIA | F134: =Hoja1!E134 -> DESARROLLO DE PROYECTOS URBANISTICOS | G134: =Hoja1!F134 -> FEMENINO | H134: =IF(C134="MATERIAS INSTITUCIONALES",1,0) -> 0 | I134: =CONCATENATE(A134,",'",B134,"','",C134,"','",D134,",'",E134,"','",F134,"','",G134,"',",H134) -> 1133,'LICENCIATURA','ARQUITECTURA','ARQ 8°','ESPINO CAMPOS NYDIA','DESARROLLO DE PROYECTOS URBANISTICOS','FEMENINO',0 | J134: =CONCATENATE($I$1,I134,");") -> INSERT INTO profesores (id,nivel,carrera,grupo,nombre,materia,sexo,sello) VALUES (1133,'LICENCIATURA','ARQUITECTURA','ARQ 8°','ESPINO CAMPOS NYDIA','DESARROLLO DE PROYECTOS URBANISTICOS','FEMENINO',0);
A135: =A134+1 -> 1134 | B135: LICENCIATURA | C135: =Hoja1!B135 -> ARQUITECTURA | D135: ARQ 8°' | E135: =Hoja1!D135 -> PEREZ GUTIERREZ JORGE HUMBERTO | F135: =Hoja1!E135 -> TOPICOS DE ACTUALIDAD | G135: =Hoja1!F135 -> MASCULINO | H135: =IF(C135="MATERIAS INSTITUCIONALES",1,0) -> 0 | I135: =CONCATENATE(A135,",'",B135,"','",C135,"','",D135,",'",E135,"','",F135,"','",G135,"',",H135) -> 1134,'LICENCIATURA','ARQUITECTURA','ARQ 8°','PEREZ GUTIERREZ JORGE HUMBERTO','TOPICOS DE ACTUALIDAD','MASCULINO',0 | J135: =CONCATENATE($I$1,I135,");") -> INSERT INTO profesores (id,nivel,carrera,grupo,nombre,materia,sexo,sello) VALUES (1134,'LICENCIATURA','ARQUITECTURA','ARQ 8°','PEREZ GUTIERREZ JORGE HUMBERTO','TOPICOS DE ACTUALIDAD','MASCULINO',0);
A136: =A135+1 -> 1135 | B136: LICENCIATURA | C136: =Hoja1!B136 -> ARQUITECTURA | D136: ARQ 8°' | E136: =Hoja1!D136 -> PONCE CUEVAS JUAN | F136: =Hoja1!E136 -> DISEÑO DEL ESPACIO PARA LA SALUD | G136: =Hoja1!F136 -> MASCULINO | H136: =IF(C136="MATERIAS INSTITUCIONALES",1,0) -> 0 | I136: =CONCATENATE(A136,",'",B136,"','",C136,"','",D136,",'",E136,"','",F136,"','",G136,"',",H136) -> 1135,'LICENCIATURA','ARQUITECTURA','ARQ 8°','PONCE CUEVAS JUAN','DISEÑO DEL ESPACIO PARA LA SALUD','MASCULINO',0 | J136: =CONCATENATE($I$1,I136,");") -> INSERT INTO profesores (id,nivel,carrera,grupo,nombre,materia,sexo,sello) VALUES (1135,'LICENCIATURA','ARQUITECTURA','ARQ 8°','PONCE CUEVAS JUAN','DISEÑO DEL ESPACIO PARA LA SALUD','MASCULINO',0);
A137: =A136+1 -> 1136 | B137: LICENCIATURA | C137: =Hoja1!B137 -> ARQUITECTURA | D137: ARQ 8°' | E137: =Hoja1!D137 -> PONCE CUEVAS JUAN | F137: =Hoja1!E137 -> GESTION Y ORGANIZACION DE OBRAS | G137: =Hoja1!F137 -> MASCULINO | H137: =IF(C137="MATERIAS INSTITUCIONALES",1,0) -> 0 | I137: =CONCATENATE(A137,",'",B137,"','",C137,"','",D137,",'",E137,"','",F137,"','",G137,"',",H137) -> 1136,'LICENCIATURA','ARQUITECTURA','ARQ 8°','PONCE CUEVAS JUAN','GESTION Y ORGANIZACION DE OBRAS','MASCULINO',0 | J137: =CONCATENATE($I$1,I137,");") -> INSERT INTO profesores (id,nivel,carrera,grupo,nombre,materia,sexo,sello) VALUES (1136,'LICENCIATURA','ARQUITECTURA','ARQ 8°','PONCE CUEVAS JUAN','GESTION Y ORGANIZACION DE OBRAS','MASCULINO',0);
A138: =A137+1 -> 1137 | B138: LICENCIATURA | C138: =Hoja1!B138 -> ARQUITECTURA | D138: ARQ 8°' | E138: =Hoja1!D138 -> SANCHEZ MUÑOZ JOSE JORGE | F138: =Hoja1!E138 -> INVESTIGACION Y APLICADA | G138: =Hoja1!F138 -> MASCULINO | H138: =IF(C138="MATERIAS INSTITUCIONALES",1,0) -> 0 | I138: =CONCATENATE(A138,",'",B138,"','",C138,"','",D138,",'",E138,"','",F138,"','",G138,"',",H138) -> 1137,'LICENCIATURA','ARQUITECTURA','ARQ 8°','SANCHEZ MUÑOZ JOSE JORGE','INVESTIGACION Y APLICADA ','MASCULINO',0 | J138: =CONCATENATE($I$1,I138,");") -> INSERT INTO profesores (id,nivel,carrera,grupo,nombre,materia,sexo,sello) VALUES (1137,'LICENCIATURA','ARQUITECTURA','ARQ 8°','SANCHEZ MUÑOZ JOSE JORGE','INVESTIGACION Y APLICADA ','MASCULINO',0);
... A189: =A188+1 -> 1188 | B189: LICENCIATURA | C189: =Hoja1!B189 -> INGENIERIA AEROESPACIAL | D189: AERO 2° B' | E189: =Hoja1!D189 -> VELA TORRES FATIMA ALEJANDRA | F189: =Hoja1!E189 -> INTRODUCCION A LA PROGRAMACION | G189: =Hoja1!F189 -> FEMENINO | H189: =IF(C189="MATERIAS INSTITUCIONALES",1,0) -> 0 | I189: =CONCATENATE(A189,",'",B189,"','",C189,"','",D189,",'",E189,"','",F189,"','",G189,"',",H189) -> 1188,'LICENCIATURA','INGENIERIA AEROESPACIAL','AERO 2° B','VELA TORRES FATIMA ALEJANDRA','INTRODUCCION A LA PROGRAMACION','FEMENINO',0 | J189: =CONCATENATE($I$1,I189,");") -> INSERT INTO profesores (id,nivel,carrera,grupo,nombre,materia,sexo,sello) VALUES (1188,'LICENCIATURA','INGENIERIA AEROESPACIAL','AERO 2° B','VELA TORRES FATIMA ALEJANDRA','INTRODUCCION A LA PROGRAMACION','FEMENINO',0);
A190: =A189+1 -> 1189 | B190: LICENCIATURA | C190: =Hoja1!B190 -> INGENIERIA AEROESPACIAL | D190: AERO 4°' | E190: NAVA CANALES CARLOS ARMANDO | F190: =Hoja1!E190 -> TERMODINAMICA | G190: =Hoja1!F190 -> MASCULINO | H190: =IF(C190="MATERIAS INSTITUCIONALES",1,0) -> 0 | I190: =CONCATENATE(A190,",'",B190,"','",C190,"','",D190,",'",E190,"','",F190,"','",G190,"',",H190) -> 1189,'LICENCIATURA','INGENIERIA AEROESPACIAL','AERO 4°','NAVA CANALES CARLOS ARMANDO','TERMODINAMICA','MASCULINO',0 | J190: =CONCATENATE($I$1,I190,");") -> INSERT INTO profesores (id,nivel,carrera,grupo,nombre,materia,sexo,sello) VALUES (1189,'LICENCIATURA','INGENIERIA AEROESPACIAL','AERO 4°','NAVA CANALES CARLOS ARMANDO','TERMODINAMICA','MASCULINO',0);
A191: =A190+1 -> 1190 | B191: LICENCIATURA | C191: =Hoja1!B191 -> INGENIERIA AEROESPACIAL | D191: AERO 4°' | E191: =Hoja1!D191 -> JIMENEZ ANDALON ENRIQUE | F191: =Hoja1!E191 -> NORMATIVA AERONAUTICA I | G191: =Hoja1!F191 -> MASCULINO | H191: =IF(C191="MATERIAS INSTITUCIONALES",1,0) -> 0 | I191: =CONCATENATE(A191,",'",B191,"','",C191,"','",D191,",'",E191,"','",F191,"','",G191,"',",H191) -> 1190,'LICENCIATURA','INGENIERIA AEROESPACIAL','AERO 4°','JIMENEZ ANDALON ENRIQUE','NORMATIVA AERONAUTICA I','MASCULINO',0 | J191: =CONCATENATE($I$1,I191,");") -> INSERT INTO profesores (id,nivel,carrera,grupo,nombre,materia,sexo,sello) VALUES (1190,'LICENCIATURA','INGENIERIA AEROESPACIAL','AERO 4°','JIMENEZ ANDALON ENRIQUE','NORMATIVA AERONAUTICA I','MASCULINO',0);
A192: =A191+1 -> 1191 | B192: LICENCIATURA | C192: =Hoja1!B192 -> INGENIERIA AEROESPACIAL | D192: AERO 4°' | E192: =Hoja1!D192 -> QUEZADA NAVARRO VICTOR MANUEL | F192: =Hoja1!E192 -> METODOS NUMERICOS | G192: =Hoja1!F192 -> MASCULINO | H192: =IF(C192="MATERIAS INSTITUCIONALES",1,0) -> 0 | I192: =CONCATENATE(A192,",'",B192,"','",C192,"','",D192,",'",E192,"','",F192,"','",G192,"',",H192) -> 1191,'LICENCIATURA','INGENIERIA AEROESPACIAL','AERO 4°','QUEZADA NAVARRO VICTOR MANUEL','METODOS NUMERICOS','MASCULINO',0 | J192: =CONCATENATE($I$1,I192,");") -> INSERT INTO profesores (id,nivel,carrera,grupo,nombre,materia,sexo,sello) VALUES (1191,'LICENCIATURA','INGENIERIA AEROESPACIAL','AERO 4°','QUEZADA NAVARRO VICTOR MANUEL','METODOS NUMERICOS','MASCULINO',0);
A193: =A192+1 -> 1192 | B193: LICENCIATURA | C193: =Hoja1!B193 -> INGENIERIA AEROESPACIAL | D193: AERO 4°' | E193: =Hoja1!D193 -> RODRIGUEZ CABRERA JUAN JOSE | F193: =Hoja1!E193 -> PLANIFICACION Y DISEÑO DE AEROPUERTOS | G193: =Hoja1!F193 -> MASCULINO | H193: =IF(C193="MATERIAS INSTITUCIONALES",1,0) -> 0 | I193: =CONCATENATE(A193,",'",B193,"','",C193,"','",D193,",'",E193,"','",F193,"','",G193,"',",H193) -> 1192,'LICENCIATURA','INGENIERIA AEROESPACIAL','AERO 4°','RODRIGUEZ CABRERA JUAN JOSE','PLANIFICACION Y DISEÑO DE AEROPUERTOS','MASCULINO',0 | J193: =CONCATENATE($I$1,I193,");") -> INSERT INTO profesores (id,nivel,carrera,grupo,nombre,materia,sexo,sello) VALUES (1192,'LICENCIATURA','INGENIERIA AEROESPACIAL','AERO 4°','RODRIGUEZ CABRERA JUAN JOSE','PLANIFICACION Y DISEÑO DE AEROPUERTOS','MASCULINO',0);
A194: =A193+1 -> 1193 | B194: LICENCIATURA | C194: =Hoja1!B194 -> INGENIERIA AEROESPACIAL | D194: AERO 4°' | E194: =Hoja1!D194 -> SANCHEZ LOPEZ FERNANDO | F194: =Hoja1!E194 -> DISEÑO Y FABRICACION ASISTIDO POR COMPUTADORA | G194: =Hoja1!F194 -> MASCULINO | H194: =IF(C194="MATERIAS INSTITUCIONALES",1,0) -> 0 | I194: =CONCATENATE(A194,",'",B194,"','",C194,"','",D194,",'",E194,"','",F194,"','",G194,"',",H194) -> 1193,'LICENCIATURA','INGENIERIA AEROESPACIAL','AERO 4°','SANCHEZ LOPEZ FERNANDO','DISEÑO Y FABRICACION ASISTIDO POR COMPUTADORA','MASCULINO',0 | J194: =CONCATENATE($I$1,I194,");") -> INSERT INTO profesores (id,nivel,carrera,grupo,nombre,materia,sexo,sello) VALUES (1193,'LICENCIATURA','INGENIERIA AEROESPACIAL','AERO 4°','SANCHEZ LOPEZ FERNANDO','DISEÑO Y FABRICACION ASISTIDO POR COMPUTADORA','MASCULINO',0);
A195: =A194+1 -> 1194 | B195: LICENCIATURA | C195: =Hoja1!B195 -> INGENIERIA AEROESPACIAL | D195: AERO 4°' | E195: =Hoja1!D195 -> SANCHEZ OCAMPO EDUARDO FRANCISCO | F195: =Hoja1!E195 -> MICROCONTROLADORES | G195: =Hoja1!F195 -> MASCULINO | H195: =IF(C195="MATERIAS INSTITUCIONALES",1,0) -> 0 | I195: =CONCATENATE(A195,",'",B195,"','",C195,"','",D195,",'",E195,"','",F195,"','",G195,"',",H195) -> 1194,'LICENCIATURA','INGENIERIA AEROESPACIAL','AERO 4°','SANCHEZ OCAMPO EDUARDO FRANCISCO','MICROCONTROLADORES','MASCULINO',0 | J195: =CONCATENATE($I$1,I195,");") -> INSERT INTO profesores (id,nivel,carrera,grupo,nombre,materia,sexo,sello) VALUES (1194,'LICENCIATURA','INGENIERIA AEROESPACIAL','AERO 4°','SANCHEZ OCAMPO EDUARDO FRANCISCO','MICROCONTROLADORES','MASCULINO',0);
A196: =A195+1 -> 1195 | B196: LICENCIATURA | C196: =Hoja1!B196 -> INGENIERIA AEROESPACIAL | D196: AERO 4°' | E196: =Hoja1!D196 -> SHINDO TAINI DAISUKE | F196: =Hoja1!E196 -> MECANICA DE FLUIDOS | G196: =Hoja1!F196 -> MASCULINO | H196: =IF(C196="MATERIAS INSTITUCIONALES",1,0) -> 0 | I196: =CONCATENATE(A196,",'",B196,"','",C196,"','",D196,",'",E196,"','",F196,"','",G196,"',",H196) -> 1195,'LICENCIATURA','INGENIERIA AEROESPACIAL','AERO 4°','SHINDO TAINI DAISUKE','MECANICA DE FLUIDOS','MASCULINO',0 | J196: =CONCATENATE($I$1,I196,");") -> INSERT INTO profesores (id,nivel,carrera,grupo,nombre,materia,sexo,sello) VALUES (1195,'LICENCIATURA','INGENIERIA AEROESPACIAL','AERO 4°','SHINDO TAINI DAISUKE','MECANICA DE FLUIDOS','MASCULINO',0);
A197: =A196+1 -> 1196 | B197: LICENCIATURA | C197: =Hoja1!B197 -> INGENIERIA AEROESPACIAL | D197: AERO 6°' | E197: =Hoja1!D197 -> GARCIA FLORES JOSE LUIS | F197: =Hoja1!E197 -> GESTION Y EXPLOTACION DE AEROPUERTOS | G197: =Hoja1!F197 -> MASCULINO | H197: =IF(C197="MATERIAS INSTITUCIONALES",1,0) -> 0 | I197: =CONCATENATE(A197,",'",B197,"','",C197,"','",D197,",'",E197,"','",F197,"','",G197,"',",H197) -> 1196,'LICENCIATURA','INGENIERIA AEROESPACIAL','AERO 6°','GARCIA FLORES JOSE LUIS','GESTION Y EXPLOTACION DE AEROPUERTOS','MASCULINO',0 | J197: =CONCATENATE($I$1,I197,");") -> INSERT INTO profesores (id,nivel,carrera,grupo,nombre,materia,sexo,sello) VALUES (1196,'LICENCIATURA','INGENIERIA AEROESPACIAL','AERO 6°','GARCIA FLORES JOSE LUIS','GESTION Y EXPLOTACION DE AEROPUERTOS','MASCULINO',0);
A198: =A197+1 -> 1197 | B198: LICENCIATURA | C198: =Hoja1!B198 -> INGENIERIA AEROESPACIAL | D198: AERO 6°' | E198: =Hoja1!D198 -> MEDINA VELAZQUEZ NANCY | F198: =Hoja1!E198 -> TRAFICO AEREO | G198: =Hoja1!F198 -> FEMENINO | H198: =IF(C198="MATERIAS INSTITUCIONALES",1,0) -> 0 | I198: =CONCATENATE(A198,",'",B198,"','",C198,"','",D198,",'",E198,"','",F198,"','",G198,"',",H198) -> 1197,'LICENCIATURA','INGENIERIA AEROESPACIAL','AERO 6°','MEDINA VELAZQUEZ NANCY','TRAFICO AEREO','FEMENINO',0 | J198: =CONCATENATE($I$1,I198,");") -> INSERT INTO profesores (id,nivel,carrera,grupo,nombre,materia,sexo,sello) VALUES (1197,'LICENCIATURA','INGENIERIA AEROESPACIAL','AERO 6°','MEDINA VELAZQUEZ NANCY','TRAFICO AEREO','FEMENINO',0);
A199: =A198+1 -> 1198 | B199: LICENCIATURA | C199: =Hoja1!B199 -> INGENIERIA AEROESPACIAL | D199: AERO 6°' | E199: =Hoja1!D199 -> MONTAÑO ALVIZO JUAN CARLOS | F199: =Hoja1!E199 -> SEÑALES Y SISTEMAS DE RADIOFRECUENCIAS | G199: =Hoja1!F199 -> MASCULINO | H199: =IF(C199="MATERIAS INSTITUCIONALES",1,0) -> 0 | I199: =CONCATENATE(A199,",'",B199,"','",C199,"','",D199,",'",E199,"','",F199,"','",G199,"',",H199) -> 1198,'LICENCIATURA','INGENIERIA AEROESPACIAL','AERO 6°','MONTAÑO ALVIZO JUAN CARLOS','SEÑALES Y SISTEMAS DE RADIOFRECUENCIAS','MASCULINO',0 | J199: =CONCATENATE($I$1,I199,");") -> INSERT INTO profesores (id,nivel,carrera,grupo,nombre,materia,sexo,sello) VALUES (1198,'LICENCIATURA','INGENIERIA AEROESPACIAL','AERO 6°','MONTAÑO ALVIZO JUAN CARLOS','SEÑALES Y SISTEMAS DE RADIOFRECUENCIAS','MASCULINO',0);
A200: =A199+1 -> 1199 | B200: LICENCIATURA | C200: =Hoja1!B200 -> INGENIERIA AEROESPACIAL | D200: AERO 6°' | E200: =Hoja1!D200 -> RODRIGUEZ CABRERA JUAN JOSE | F200: =Hoja1!E200 -> SISTEMAS DE AERONAVES I | G200: =Hoja1!F200 -> MASCULINO | H200: =IF(C200="MATERIAS INSTITUCIONALES",1,0) -> 0 | I200: =CONCATENATE(A200,",'",B200,"','",C200,"','",D200,",'",E200,"','",F200,"','",G200,"',",H200) -> 1199,'LICENCIATURA','INGENIERIA AEROESPACIAL','AERO 6°','RODRIGUEZ CABRERA JUAN JOSE','SISTEMAS DE AERONAVES I','MASCULINO',0 | J200: =CONCATENATE($I$1,I200,");") -> INSERT INTO profesores (id,nivel,carrera,grupo,nombre,materia,sexo,sello) VALUES (1199,'LICENCIATURA','INGENIERIA AEROESPACIAL','AERO 6°','RODRIGUEZ CABRERA JUAN JOSE','SISTEMAS DE AERONAVES I','MASCULINO',0);
A201: =A200+1 -> 1200 | B201: LICENCIATURA | C201: =Hoja1!B201 -> INGENIERIA AEROESPACIAL | D201: AERO 6°' | E201: =Hoja1!D201 -> RODRIGUEZ MIRANDA JOSE BENJAMIN | F201: =Hoja1!E201 -> MOTORES RECIPROCOS Y SUS SISTEMAS | G201: =Hoja1!F201 -> MASCULINO | H201: =IF(C201="MATERIAS INSTITUCIONALES",1,0) -> 0 | I201: =CONCATENATE(A201,",'",B201,"','",C201,"','",D201,",'",E201,"','",F201,"','",G201,"',",H201) -> 1200,'LICENCIATURA','INGENIERIA AEROESPACIAL','AERO 6°','RODRIGUEZ MIRANDA JOSE BENJAMIN','MOTORES RECIPROCOS Y SUS SISTEMAS','MASCULINO',0 | J201: =CONCATENATE($I$1,I201,");") -> INSERT INTO profesores (id,nivel,carrera,grupo,nombre,materia,sexo,sello) VALUES (1200,'LICENCIATURA','INGENIERIA AEROESPACIAL','AERO 6°','RODRIGUEZ MIRANDA JOSE BENJAMIN','MOTORES RECIPROCOS Y SUS SISTEMAS','MASCULINO',0);
A202: =A201+1 -> 1201 | B202: LICENCIATURA | C202: =Hoja1!B202 -> INGENIERIA AEROESPACIAL | D202: AERO 6°' | E202: =Hoja1!D202 -> ZARATE TOMAS CIRO | F202: =Hoja1!E202 -> MECANICA DE VUELOS | G202: =Hoja1!F202 -> MASCULINO | H202: =IF(C202="MATERIAS INSTITUCIONALES",1,0) -> 0 | I202: =CONCATENATE(A202,",'",B202,"','",C202,"','",D202,",'",E202,"','",F202,"','",G202,"',",H202) -> 1201,'LICENCIATURA','INGENIERIA AEROESPACIAL','AERO 6°','ZARATE TOMAS CIRO','MECANICA DE VUELOS','MASCULINO',0 | J202: =CONCATENATE($I$1,I202,");") -> INSERT INTO profesores (id,nivel,carrera,grupo,nombre,materia,sexo,sello) VALUES (1201,'LICENCIATURA','INGENIERIA AEROESPACIAL','AERO 6°','ZARATE TOMAS CIRO','MECANICA DE VUELOS','MASCULINO',0);
... A208: =A207+1 -> 1207 | B208: LICENCIATURA | C208: =Hoja1!B208 -> INGENIERIA AEROESPACIAL | D208: AERO_10°' | E208: =Hoja1!D208 -> LARA FAVELA DANIEL | F208: =Hoja1!E208 -> DISEÑO PRELIMINAR DE NAVES ESPACIALES | G208: =Hoja1!F208 -> MASCULINO | H208: =IF(C208="MATERIAS INSTITUCIONALES",1,0) -> 0 | I208: =CONCATENATE(A208,",'",B208,"','",C208,"','",D208,",'",E208,"','",F208,"','",G208,"',",H208) -> 1207,'LICENCIATURA','INGENIERIA AEROESPACIAL','AERO_10°','LARA FAVELA DANIEL','DISEÑO PRELIMINAR DE NAVES ESPACIALES','MASCULINO',0 | J208: =CONCATENATE($I$1,I208,");") -> INSERT INTO profesores (id,nivel,carrera,grupo,nombre,materia,sexo,sello) VALUES (1207,'LICENCIATURA','INGENIERIA AEROESPACIAL','AERO_10°','LARA FAVELA DANIEL','DISEÑO PRELIMINAR DE NAVES ESPACIALES','MASCULINO',0);
A209: =A208+1 -> 1208 | B209: LICENCIATURA | C209: =Hoja1!B209 -> INGENIERIA AEROESPACIAL | D209: AERO_10°' | E209: MÉNDEZ JIMÉNEZ ALBERTO | F209: =Hoja1!E209 -> AUTOMATIZACION DE LA FABRIACACION | G209: =Hoja1!F209 -> MASCULINO | H209: =IF(C209="MATERIAS INSTITUCIONALES",1,0) -> 0 | I209: =CONCATENATE(A209,",'",B209,"','",C209,"','",D209,",'",E209,"','",F209,"','",G209,"',",H209) -> 1208,'LICENCIATURA','INGENIERIA AEROESPACIAL','AERO_10°','MÉNDEZ JIMÉNEZ ALBERTO','AUTOMATIZACION DE LA FABRIACACION','MASCULINO',0 | J209: =CONCATENATE($I$1,I209,");") -> INSERT INTO profesores (id,nivel,carrera,grupo,nombre,materia,sexo,sello) VALUES (1208,'LICENCIATURA','INGENIERIA AEROESPACIAL','AERO_10°','MÉNDEZ JIMÉNEZ ALBERTO','AUTOMATIZACION DE LA FABRIACACION','MASCULINO',0);
A210: =A209+1 -> 1209 | B210: LICENCIATURA | C210: =Hoja1!B210 -> INGENIERIA AEROESPACIAL | D210: AERO_10°' | E210: =Hoja1!D210 -> RODRIGUEZ MIRANDA JOSE BENJAMIN | F210: =Hoja1!E210 -> TOPICOS DE ACTUALIDAD EN INGENIERIA AEROESPACIAL | G210: =Hoja1!F210 -> MASCULINO | H210: =IF(C210="MATERIAS INSTITUCIONALES",1,0) -> 0 | I210: =CONCATENATE(A210,",'",B210,"','",C210,"','",D210,",'",E210,"','",F210,"','",G210,"',",H210) -> 1209,'LICENCIATURA','INGENIERIA AEROESPACIAL','AERO_10°','RODRIGUEZ MIRANDA JOSE BENJAMIN','TOPICOS DE ACTUALIDAD EN INGENIERIA AEROESPACIAL','MASCULINO',0 | J210: =CONCATENATE($I$1,I210,");") -> INSERT INTO profesores (id,nivel,carrera,grupo,nombre,materia,sexo,sello) VALUES (1209,'LICENCIATURA','INGENIERIA AEROESPACIAL','AERO_10°','RODRIGUEZ MIRANDA JOSE BENJAMIN','TOPICOS DE ACTUALIDAD EN INGENIERIA AEROESPACIAL','MASCULINO',0);
A211: =A210+1 -> 1210 | B211: LICENCIATURA | C211: =Hoja1!B211 -> INGENIERIA AEROESPACIAL | D211: AERO_10°' | E211: =Hoja1!D211 -> ZARATE TOMAS CIRO | F211: =Hoja1!E211 -> ESTRUCTURAS ESPACIALES | G211: =Hoja1!F211 -> MASCULINO | H211: =IF(C211="MATERIAS INSTITUCIONALES",1,0) -> 0 | I211: =CONCATENATE(A211,",'",B211,"','",C211,"','",D211,",'",E211,"','",F211,"','",G211,"',",H211) -> 1210,'LICENCIATURA','INGENIERIA AEROESPACIAL','AERO_10°','ZARATE TOMAS CIRO','ESTRUCTURAS ESPACIALES','MASCULINO',0 | J211: =CONCATENATE($I$1,I211,");") -> INSERT INTO profesores (id,nivel,carrera,grupo,nombre,materia,sexo,sello) VALUES (1210,'LICENCIATURA','INGENIERIA AEROESPACIAL','AERO_10°','ZARATE TOMAS CIRO','ESTRUCTURAS ESPACIALES','MASCULINO',0);
A212: =A211+1 -> 1211 | B212: LICENCIATURA | C212: =Hoja1!B212 -> INGENIERÍA AUTOMOTRIZ | D212: AUTO 2° A' | E212: =Hoja1!D212 -> CARDENAS CASTILLO SANTIAGO | F212: =Hoja1!E212 -> METROLOGIA | G212: =Hoja1!F212 -> MASCULINO | H212: =IF(C212="MATERIAS INSTITUCIONALES",1,0) -> 0 | I212: =CONCATENATE(A212,",'",B212,"','",C212,"','",D212,",'",E212,"','",F212,"','",G212,"',",H212) -> 1211,'LICENCIATURA','INGENIERÍA AUTOMOTRIZ','AUTO 2° A','CARDENAS CASTILLO SANTIAGO','METROLOGIA','MASCULINO',0 | J212: =CONCATENATE($I$1,I212,");") -> INSERT INTO profesores (id,nivel,carrera,grupo,nombre,materia,sexo,sello) VALUES (1211,'LICENCIATURA','INGENIERÍA AUTOMOTRIZ','AUTO 2° A','CARDENAS CASTILLO SANTIAGO','METROLOGIA','MASCULINO',0);
A213: =A212+1 -> 1212 | B213: LICENCIATURA | C213: =Hoja1!B213 -> INGENIERÍA AUTOMOTRIZ | D213: AUTO 2° A' | E213: =Hoja1!D213 -> FRANCO DE JESUS LEONARDO | F213: =Hoja1!E213 -> MAQUINAS Y HERRAMIENTAS | G213: =Hoja1!F213 -> MASCULINO | H213: =IF(C213="MATERIAS INSTITUCIONALES",1,0) -> 0 | I213: =CONCATENATE(A213,",'",B213,"','",C213,"','",D213,",'",E213,"','",F213,"','",G213,"',",H213) -> 1212,'LICENCIATURA','INGENIERÍA AUTOMOTRIZ','AUTO 2° A','FRANCO DE JESUS LEONARDO','MAQUINAS Y HERRAMIENTAS ','MASCULINO',0 | J213: =CONCATENATE($I$1,I213,");") -> INSERT INTO profesores (id,nivel,carrera,grupo,nombre,materia,sexo,sello) VALUES (1212,'LICENCIATURA','INGENIERÍA AUTOMOTRIZ','AUTO 2° A','FRANCO DE JESUS LEONARDO','MAQUINAS Y HERRAMIENTAS ','MASCULINO',0);
A214: =A213+1 -> 1213 | B214: LICENCIATURA | C214: =Hoja1!B214 -> INGENIERÍA AUTOMOTRIZ | D214: AUTO 2° A' | E214: =Hoja1!D214 -> HERNANDEZ ESPINOSA DANIEL | F214: =Hoja1!E214 -> DIBUJO ASISTIDO POR COMPUTADORA I | G214: =Hoja1!F214 -> MASCULINO | H214: =IF(C214="MATERIAS INSTITUCIONALES",1,0) -> 0 | I214: =CONCATENATE(A214,",'",B214,"','",C214,"','",D214,",'",E214,"','",F214,"','",G214,"',",H214) -> 1213,'LICENCIATURA','INGENIERÍA AUTOMOTRIZ','AUTO 2° A','HERNANDEZ ESPINOSA DANIEL','DIBUJO ASISTIDO POR COMPUTADORA I','MASCULINO',0 | J214: =CONCATENATE($I$1,I214,");") -> INSERT INTO profesores (id,nivel,carrera,grupo,nombre,materia,sexo,sello) VALUES (1213,'LICENCIATURA','INGENIERÍA AUTOMOTRIZ','AUTO 2° A','HERNANDEZ ESPINOSA DANIEL','DIBUJO ASISTIDO POR COMPUTADORA I','MASCULINO',0);
A215: =A214+1 -> 1214 | B215: LICENCIATURA | C215: =Hoja1!B215 -> INGENIERÍA AUTOMOTRIZ | D215: AUTO 2° A' | E215: =Hoja1!D215 -> HERNANDEZ MONTES JAZMIN | F215: =Hoja1!E215 -> ALGEBRA LINEAL | G215: =Hoja1!F215 -> FEMENINO | H215: =IF(C215="MATERIAS INSTITUCIONALES",1,0) -> 0 | I215: =CONCATENATE(A215,",'",B215,"','",C215,"','",D215,",'",E215,"','",F215,"','",G215,"',",H215) -> 1214,'LICENCIATURA','INGENIERÍA AUTOMOTRIZ','AUTO 2° A','HERNANDEZ MONTES JAZMIN','ALGEBRA LINEAL ','FEMENINO',0 | J215: =CONCATENATE($I$1,I215,");") -> INSERT INTO profesores (id,nivel,carrera,grupo,nombre,materia,sexo,sello) VALUES (1214,'LICENCIATURA','INGENIERÍA AUTOMOTRIZ','AUTO 2° A','HERNANDEZ MONTES JAZMIN','ALGEBRA LINEAL ','FEMENINO',0);
A216: =A215+1 -> 1215 | B216: LICENCIATURA | C216: =Hoja1!B216 -> INGENIERÍA AUTOMOTRIZ | D216: AUTO 2° A' | E216: =Hoja1!D216 -> MACIAS GARZA JORGE ENRIQUE | F216: =Hoja1!E216 -> CIRCUITOS LOGICOS | G216: =Hoja1!F216 -> MASCULINO | H216: =IF(C216="MATERIAS INSTITUCIONALES",1,0) -> 0 | I216: =CONCATENATE(A216,",'",B216,"','",C216,"','",D216,",'",E216,"','",F216,"','",G216,"',",H216) -> 1215,'LICENCIATURA','INGENIERÍA AUTOMOTRIZ','AUTO 2° A','MACIAS GARZA JORGE ENRIQUE','CIRCUITOS LOGICOS ','MASCULINO',0 | J216: =CONCATENATE($I$1,I216,");") -> INSERT INTO profesores (id,nivel,carrera,grupo,nombre,materia,sexo,sello) VALUES (1215,'LICENCIATURA','INGENIERÍA AUTOMOTRIZ','AUTO 2° A','MACIAS GARZA JORGE ENRIQUE','CIRCUITOS LOGICOS ','MASCULINO',0);
A217: =A216+1 -> 1216 | B217: LICENCIATURA | C217: =Hoja1!B217 -> INGENIERÍA AUTOMOTRIZ | D217: AUTO 2° A' | E217: =Hoja1!D217 -> SALDIVAR OROZCO EMMANUEL | F217: =Hoja1!E217 -> DINAMICA | G217: =Hoja1!F217 -> MASCULINO | H217: =IF(C217="MATERIAS INSTITUCIONALES",1,0) -> 0 | I217: =CONCATENATE(A217,",'",B217,"','",C217,"','",D217,",'",E217,"','",F217,"','",G217,"',",H217) -> 1216,'LICENCIATURA','INGENIERÍA AUTOMOTRIZ','AUTO 2° A','SALDIVAR OROZCO EMMANUEL','DINAMICA ','MASCULINO',0 | J217: =CONCATENATE($I$1,I217,");") -> INSERT INTO profesores (id,nivel,carrera,grupo,nombre,materia,sexo,sello) VALUES (1216,'LICENCIATURA','INGENIERÍA AUTOMOTRIZ','AUTO 2° A','SALDIVAR OROZCO EMMANUEL','DINAMICA ','MASCULINO',0);
A218: =A217+1 -> 1217 | B218: LICENCIATURA | C218: =Hoja1!B218 -> INGENIERÍA AUTOMOTRIZ | D218: AUTO 2° B' | E218: =Hoja1!D218 -> CARDENAS CASTILLO SANTIAGO | F218: =Hoja1!E218 -> METROLOGIA | G218: =Hoja1!F218 -> MASCULINO | H218: =IF(C218="MATERIAS INSTITUCIONALES",1,0) -> 0 | I218: =CONCATENATE(A218,",'",B218,"','",C218,"','",D218,",'",E218,"','",F218,"','",G218,"',",H218) -> 1217,'LICENCIATURA','INGENIERÍA AUTOMOTRIZ','AUTO 2° B','CARDENAS CASTILLO SANTIAGO','METROLOGIA','MASCULINO',0 | J218: =CONCATENATE($I$1,I218,");") -> INSERT INTO profesores (id,nivel,carrera,grupo,nombre,materia,sexo,sello) VALUES (1217,'LICENCIATURA','INGENIERÍA AUTOMOTRIZ','AUTO 2° B','CARDENAS CASTILLO SANTIAGO','METROLOGIA','MASCULINO',0);
A219: =A218+1 -> 1218 | B219: LICENCIATURA | C219: =Hoja1!B219 -> INGENIERÍA AUTOMOTRIZ | D219: AUTO 2° B' | E219: =Hoja1!D219 -> FRANCO DE JESUS LEONARDO | F219: =Hoja1!E219 -> MAQUINAS Y HERRAMIENTAS | G219: =Hoja1!F219 -> MASCULINO | H219: =IF(C219="MATERIAS INSTITUCIONALES",1,0) -> 0 | I219: =CONCATENATE(A219,",'",B219,"','",C219,"','",D219,",'",E219,"','",F219,"','",G219,"',",H219) -> 1218,'LICENCIATURA','INGENIERÍA AUTOMOTRIZ','AUTO 2° B','FRANCO DE JESUS LEONARDO','MAQUINAS Y HERRAMIENTAS ','MASCULINO',0 | J219: =CONCATENATE($I$1,I219,");") -> INSERT INTO profesores (id,nivel,carrera,grupo,nombre,materia,sexo,sello) VALUES (1218,'LICENCIATURA','INGENIERÍA AUTOMOTRIZ','AUTO 2° B','FRANCO DE JESUS LEONARDO','MAQUINAS Y HERRAMIENTAS ','MASCULINO',0);
A220: =A219+1 -> 1219 | B220: LICENCIATURA | C220: =Hoja1!B220 -> INGENIERÍA AUTOMOTRIZ | D220: AUTO 2° B' | E220: =Hoja1!D220 -> HERNANDEZ ESPINOSA DANIEL | F220: =Hoja1!E220 -> DIBUJO ASISTIDO POR COMPUTADORA I | G220: =Hoja1!F220 -> MASCULINO | H220: =IF(C220="MATERIAS INSTITUCIONALES",1,0) -> 0 | I220: =CONCATENATE(A220,",'",B220,"','",C220,"','",D220,",'",E220,"','",F220,"','",G220,"',",H220) -> 1219,'LICENCIATURA','INGENIERÍA AUTOMOTRIZ','AUTO 2° B','HERNANDEZ ESPINOSA DANIEL','DIBUJO ASISTIDO POR COMPUTADORA I','MASCULINO',0 | J220: =CONCATENATE($I$1,I220,");") -> INSERT INTO profesores (id,nivel,carrera,grupo,nombre,materia,sexo,sello) VALUES (1219,'LICENCIATURA','INGENIERÍA AUTOMOTRIZ','AUTO 2° B','HERNANDEZ ESPINOSA DANIEL','DIBUJO ASISTIDO POR COMPUTADORA I','MASCULINO',0);
A221: =A220+1 -> 1220 | B221: LICENCIATURA | C221: =Hoja1!B221 -> INGENIERÍA AUTOMOTRIZ | D221: AUTO 2° B' | E221: =Hoja1!D221 -> HERNANDEZ MONTES JAZMIN | F221: =Hoja1!E221 -> ALGEBRA LINEAL | G221: =Hoja1!F221 -> FEMENINO | H221: =IF(C221="MATERIAS INSTITUCIONALES",1,0) -> 0 | I221: =CONCATENATE(A221,",'",B221,"','",C221,"','",D221,",'",E221,"','",F221,"','",G221,"',",H221) -> 1220,'LICENCIATURA','INGENIERÍA AUTOMOTRIZ','AUTO 2° B','HERNANDEZ MONTES JAZMIN','ALGEBRA LINEAL ','FEMENINO',0 | J221: =CONCATENATE($I$1,I221,");") -> INSERT INTO profesores (id,nivel,carrera,grupo,nombre,materia,sexo,sello) VALUES (1220,'LICENCIATURA','INGENIERÍA AUTOMOTRIZ','AUTO 2° B','HERNANDEZ MONTES JAZMIN','ALGEBRA LINEAL ','FEMENINO',0);
... A236: =A235+1 -> 1235 | B236: LICENCIATURA | C236: =Hoja1!B236 -> INGENIERIA CIBERNETICA Y EN SISTEMAS COMPUTACIONALES | D236: CIB 4°' | E236: =Hoja1!D236 -> NUÑEZ VELAZQUEZ ANA MARIA | F236: =Hoja1!E236 -> ELECTRONICA AVANZADA | G236: =Hoja1!F236 -> FEMENINO | H236: =IF(C236="MATERIAS INSTITUCIONALES",1,0) -> 0 | I236: =CONCATENATE(A236,",'",B236,"','",C236,"','",D236,",'",E236,"','",F236,"','",G236,"',",H236) -> 1235,'LICENCIATURA','INGENIERIA CIBERNETICA Y EN SISTEMAS COMPUTACIONALES','CIB 4°','NUÑEZ VELAZQUEZ ANA MARIA ','ELECTRONICA AVANZADA','FEMENINO',0 | J236: =CONCATENATE($I$1,I236,");") -> INSERT INTO profesores (id,nivel,carrera,grupo,nombre,materia,sexo,sello) VALUES (1235,'LICENCIATURA','INGENIERIA CIBERNETICA Y EN SISTEMAS COMPUTACIONALES','CIB 4°','NUÑEZ VELAZQUEZ ANA MARIA ','ELECTRONICA AVANZADA','FEMENINO',0);
A237: =A236+1 -> 1236 | B237: LICENCIATURA | C237: =Hoja1!B237 -> INGENIERIA CIBERNETICA Y EN SISTEMAS COMPUTACIONALES | D237: CIB 6°' | E237: DE LEÓN SÁNCHEZ JOSÉ ISRAEL | F237: =Hoja1!E237 -> BASE DE DATOS NO RELACIONALES | G237: =Hoja1!F237 -> MASCULINO | H237: =IF(C237="MATERIAS INSTITUCIONALES",1,0) -> 0 | I237: =CONCATENATE(A237,",'",B237,"','",C237,"','",D237,",'",E237,"','",F237,"','",G237,"',",H237) -> 1236,'LICENCIATURA','INGENIERIA CIBERNETICA Y EN SISTEMAS COMPUTACIONALES','CIB 6°','DE LEÓN SÁNCHEZ JOSÉ ISRAEL','BASE DE DATOS NO RELACIONALES','MASCULINO',0 | J237: =CONCATENATE($I$1,I237,");") -> INSERT INTO profesores (id,nivel,carrera,grupo,nombre,materia,sexo,sello) VALUES (1236,'LICENCIATURA','INGENIERIA CIBERNETICA Y EN SISTEMAS COMPUTACIONALES','CIB 6°','DE LEÓN SÁNCHEZ JOSÉ ISRAEL','BASE DE DATOS NO RELACIONALES','MASCULINO',0);
A238: =A237+1 -> 1237 | B238: LICENCIATURA | C238: =Hoja1!B238 -> INGENIERIA CIBERNETICA Y EN SISTEMAS COMPUTACIONALES | D238: CIB 6°' | E238: =Hoja1!D238 -> DELGADILLO BOCANEGRA JOSE DE JESUS | F238: =Hoja1!E238 -> ROBOTICA | G238: =Hoja1!F238 -> MASCULINO | H238: =IF(C238="MATERIAS INSTITUCIONALES",1,0) -> 0 | I238: =CONCATENATE(A238,",'",B238,"','",C238,"','",D238,",'",E238,"','",F238,"','",G238,"',",H238) -> 1237,'LICENCIATURA','INGENIERIA CIBERNETICA Y EN SISTEMAS COMPUTACIONALES','CIB 6°','DELGADILLO BOCANEGRA JOSE DE JESUS','ROBOTICA','MASCULINO',0 | J238: =CONCATENATE($I$1,I238,");") -> INSERT INTO profesores (id,nivel,carrera,grupo,nombre,materia,sexo,sello) VALUES (1237,'LICENCIATURA','INGENIERIA CIBERNETICA Y EN SISTEMAS COMPUTACIONALES','CIB 6°','DELGADILLO BOCANEGRA JOSE DE JESUS','ROBOTICA','MASCULINO',0);
A239: =A238+1 -> 1238 | B239: LICENCIATURA | C239: =Hoja1!B239 -> INGENIERIA CIBERNETICA Y EN SISTEMAS COMPUTACIONALES | D239: CIB 6°' | E239: =Hoja1!D239 -> GARCIA HERNANDEZ MARTIN | F239: =Hoja1!E239 -> TEORIA DE AUTOMATAS Y LENGUAJES FORMALES | G239: =Hoja1!F239 -> MASCULINO | H239: =IF(C239="MATERIAS INSTITUCIONALES",1,0) -> 0 | I239: =CONCATENATE(A239,",'",B239,"','",C239,"','",D239,",'",E239,"','",F239,"','",G239,"',",H239) -> 1238,'LICENCIATURA','INGENIERIA CIBERNETICA Y EN SISTEMAS COMPUTACIONALES','CIB 6°','GARCIA HERNANDEZ MARTIN','TEORIA DE AUTOMATAS Y LENGUAJES FORMALES','MASCULINO',0 | J239: =CONCATENATE($I$1,I239,");") -> INSERT INTO profesores (id,nivel,carrera,grupo,nombre,materia,sexo,sello) VALUES (1238,'LICENCIATURA','INGENIERIA CIBERNETICA Y EN SISTEMAS COMPUTACIONALES','CIB 6°','GARCIA HERNANDEZ MARTIN','TEORIA DE AUTOMATAS Y LENGUAJES FORMALES','MASCULINO',0);
A240: =A239+1 -> 1239 | B240: LICENCIATURA | C240: =Hoja1!B240 -> INGENIERIA CIBERNETICA Y EN SISTEMAS COMPUTACIONALES | D240: CIB 6°' | E240: =Hoja1!D240 -> MADRIGAL RODRIGUEZ GRISELDA | F240: =Hoja1!E240 -> METRICAS DE SOFTWARE Y PRUEBAS UNITARIAS | G240: =Hoja1!F240 -> FEMENINO | H240: =IF(C240="MATERIAS INSTITUCIONALES",1,0) -> 0 | I240: =CONCATENATE(A240,",'",B240,"','",C240,"','",D240,",'",E240,"','",F240,"','",G240,"',",H240) -> 1239,'LICENCIATURA','INGENIERIA CIBERNETICA Y EN SISTEMAS COMPUTACIONALES','CIB 6°','MADRIGAL RODRIGUEZ GRISELDA','METRICAS DE SOFTWARE Y PRUEBAS UNITARIAS','FEMENINO',0 | J240: =CONCATENATE($I$1,I240,");") -> INSERT INTO profesores (id,nivel,carrera,grupo,nombre,materia,sexo,sello) VALUES (1239,'LICENCIATURA','INGENIERIA CIBERNETICA Y EN SISTEMAS COMPUTACIONALES','CIB 6°','MADRIGAL RODRIGUEZ GRISELDA','METRICAS DE SOFTWARE Y PRUEBAS UNITARIAS','FEMENINO',0);
A241: =A240+1 -> 1240 | B241: LICENCIATURA | C241: =Hoja1!B241 -> INGENIERIA CIBERNETICA Y EN SISTEMAS COMPUTACIONALES | D241: CIB 6°' | E241: =Hoja1!D241 -> MONTAÑO ALVIZO JUAN CARLOS | F241: =Hoja1!E241 -> SISTEMAS EMBEBIDOS | G241: =Hoja1!F241 -> MASCULINO | H241: =IF(C241="MATERIAS INSTITUCIONALES",1,0) -> 0 | I241: =CONCATENATE(A241,",'",B241,"','",C241,"','",D241,",'",E241,"','",F241,"','",G241,"',",H241) -> 1240,'LICENCIATURA','INGENIERIA CIBERNETICA Y EN SISTEMAS COMPUTACIONALES','CIB 6°','MONTAÑO ALVIZO JUAN CARLOS','SISTEMAS EMBEBIDOS','MASCULINO',0 | J241: =CONCATENATE($I$1,I241,");") -> INSERT INTO profesores (id,nivel,carrera,grupo,nombre,materia,sexo,sello) VALUES (1240,'LICENCIATURA','INGENIERIA CIBERNETICA Y EN SISTEMAS COMPUTACIONALES','CIB 6°','MONTAÑO ALVIZO JUAN CARLOS','SISTEMAS EMBEBIDOS','MASCULINO',0);
A242: =A241+1 -> 1241 | B242: LICENCIATURA | C242: =Hoja1!B242 -> INGENIERIA CIBERNETICA Y EN SISTEMAS COMPUTACIONALES | D242: CIB 8°' | E242: =Hoja1!D242 -> BAEZA MONTIEL RICARDO IGNACIO | F242: =Hoja1!E242 -> COMPILADORES | G242: =Hoja1!F242 -> MASCULINO | H242: =IF(C242="MATERIAS INSTITUCIONALES",1,0) -> 0 | I242: =CONCATENATE(A242,",'",B242,"','",C242,"','",D242,",'",E242,"','",F242,"','",G242,"',",H242) -> 1241,'LICENCIATURA','INGENIERIA CIBERNETICA Y EN SISTEMAS COMPUTACIONALES','CIB 8°','BAEZA MONTIEL RICARDO IGNACIO','COMPILADORES','MASCULINO',0 | J242: =CONCATENATE($I$1,I242,");") -> INSERT INTO profesores (id,nivel,carrera,grupo,nombre,materia,sexo,sello) VALUES (1241,'LICENCIATURA','INGENIERIA CIBERNETICA Y EN SISTEMAS COMPUTACIONALES','CIB 8°','BAEZA MONTIEL RICARDO IGNACIO','COMPILADORES','MASCULINO',0);
A243: =A242+1 -> 1242 | B243: LICENCIATURA | C243: =Hoja1!B243 -> INGENIERIA CIBERNETICA Y EN SISTEMAS COMPUTACIONALES | D243: CIB 8°' | E243: =Hoja1!D243 -> BAEZA MONTIEL RICARDO IGNACIO | F243: =Hoja1!E243 -> SEGURIDAD Y AUDITORIA INFORMATICA | G243: =Hoja1!F243 -> MASCULINO | H243: =IF(C243="MATERIAS INSTITUCIONALES",1,0) -> 0 | I243: =CONCATENATE(A243,",'",B243,"','",C243,"','",D243,",'",E243,"','",F243,"','",G243,"',",H243) -> 1242,'LICENCIATURA','INGENIERIA CIBERNETICA Y EN SISTEMAS COMPUTACIONALES','CIB 8°','BAEZA MONTIEL RICARDO IGNACIO','SEGURIDAD Y AUDITORIA INFORMATICA','MASCULINO',0 | J243: =CONCATENATE($I$1,I243,");") -> INSERT INTO profesores (id,nivel,carrera,grupo,nombre,materia,sexo,sello) VALUES (1242,'LICENCIATURA','INGENIERIA CIBERNETICA Y EN SISTEMAS COMPUTACIONALES','CIB 8°','BAEZA MONTIEL RICARDO IGNACIO','SEGURIDAD Y AUDITORIA INFORMATICA','MASCULINO',0);
A244: =A243+1 -> 1243 | B244: LICENCIATURA | C244: =Hoja1!B244 -> INGENIERIA CIBERNETICA Y EN SISTEMAS COMPUTACIONALES | D244: CIB 8°' | E244: DE LEÓN SÁNCHEZ JOSÉ ISRAEL | F244: COMPLEJIDAD DE ALGORITMOS | G244: =Hoja1!F244 -> MASCULINO | H244: =IF(C244="MATERIAS INSTITUCIONALES",1,0) -> 0 | I244: =CONCATENATE(A244,",'",B244,"','",C244,"','",D244,",'",E244,"','",F244,"','",G244,"',",H244) -> 1243,'LICENCIATURA','INGENIERIA CIBERNETICA Y EN SISTEMAS COMPUTACIONALES','CIB 8°','DE LEÓN SÁNCHEZ JOSÉ ISRAEL','COMPLEJIDAD DE ALGORITMOS','MASCULINO',0 | J244: =CONCATENATE($I$1,I244,");") -> INSERT INTO profesores (id,nivel,carrera,grupo,nombre,materia,sexo,sello) VALUES (1243,'LICENCIATURA','INGENIERIA CIBERNETICA Y EN SISTEMAS COMPUTACIONALES','CIB 8°','DE LEÓN SÁNCHEZ JOSÉ ISRAEL','COMPLEJIDAD DE ALGORITMOS','MASCULINO',0);
A245: =A244+1 -> 1244 | B245: LICENCIATURA | C245: =Hoja1!B245 -> INGENIERIA CIBERNETICA Y EN SISTEMAS COMPUTACIONALES | D245: CIB 8°' | E245: =Hoja1!D245 -> RUIZ AREVALO ALDO MACIEL | F245: =Hoja1!E245 -> MINERIA DE DATOS | G245: =Hoja1!F245 -> MASCULINO | H245: =IF(C245="MATERIAS INSTITUCIONALES",1,0) -> 0 | I245: =CONCATENATE(A245,",'",B245,"','",C245,"','",D245,",'",E245,"','",F245,"','",G245,"',",H245) -> 1244,'LICENCIATURA','INGENIERIA CIBERNETICA Y EN SISTEMAS COMPUTACIONALES','CIB 8°','RUIZ AREVALO ALDO MACIEL','MINERIA DE DATOS','MASCULINO',0 | J245: =CONCATENATE($I$1,I245,");") -> INSERT INTO profesores (id,nivel,carrera,grupo,nombre,materia,sexo,sello) VALUES (1244,'LICENCIATURA','INGENIERIA CIBERNETICA Y EN SISTEMAS COMPUTACIONALES','CIB 8°','RUIZ AREVALO ALDO MACIEL','MINERIA DE DATOS','MASCULINO',0);
A246: =A245+1 -> 1245 | B246: LICENCIATURA | C246: =Hoja1!B246 -> INGENIERÍA EN INTELIGENCIA ARTIFICIAL | D246: IA 2°' | E246: =Hoja1!D246 -> GARCIA SANCHEZ MARIA LUISA | F246: =Hoja1!E246 -> SISTEMAS OPERATIVOS | G246: =Hoja1!F246 -> FEMENINO | H246: =IF(C246="MATERIAS INSTITUCIONALES",1,0) -> 0 | I246: =CONCATENATE(A246,",'",B246,"','",C246,"','",D246,",'",E246,"','",F246,"','",G246,"',",H246) -> 1245,'LICENCIATURA','INGENIERÍA EN INTELIGENCIA ARTIFICIAL','IA 2°','GARCIA SANCHEZ MARIA LUISA ','SISTEMAS OPERATIVOS ','FEMENINO',0 | J246: =CONCATENATE($I$1,I246,");") -> INSERT INTO profesores (id,nivel,carrera,grupo,nombre,materia,sexo,sello) VALUES (1245,'LICENCIATURA','INGENIERÍA EN INTELIGENCIA ARTIFICIAL','IA 2°','GARCIA SANCHEZ MARIA LUISA ','SISTEMAS OPERATIVOS ','FEMENINO',0);
A247: =A246+1 -> 1246 | B247: LICENCIATURA | C247: =Hoja1!B247 -> INGENIERÍA EN INTELIGENCIA ARTIFICIAL | D247: IA 2°' | E247: =Hoja1!D247 -> GAYTAN GODINEZ LORENA | F247: =Hoja1!E247 -> PROGRAMACIÓN ORIENTADA A OBJETOS | G247: =Hoja1!F247 -> FEMENINO | H247: =IF(C247="MATERIAS INSTITUCIONALES",1,0) -> 0 | I247: =CONCATENATE(A247,",'",B247,"','",C247,"','",D247,",'",E247,"','",F247,"','",G247,"',",H247) -> 1246,'LICENCIATURA','INGENIERÍA EN INTELIGENCIA ARTIFICIAL','IA 2°','GAYTAN GODINEZ LORENA','PROGRAMACIÓN ORIENTADA A OBJETOS ','FEMENINO',0 | J247: =CONCATENATE($I$1,I247,");") -> INSERT INTO profesores (id,nivel,carrera,grupo,nombre,materia,sexo,sello) VALUES (1246,'LICENCIATURA','INGENIERÍA EN INTELIGENCIA ARTIFICIAL','IA 2°','GAYTAN GODINEZ LORENA','PROGRAMACIÓN ORIENTADA A OBJETOS ','FEMENINO',0);
A248: =A247+1 -> 1247 | B248: LICENCIATURA | C248: =Hoja1!B248 -> INGENIERÍA EN INTELIGENCIA ARTIFICIAL | D248: IA 2°' | E248: =Hoja1!D248 -> MARTINEZ ALVARADO JUAN CARLOS | F248: =Hoja1!E248 -> CÁLCULO MULTIVARIABLE | G248: =Hoja1!F248 -> MASCULINO | H248: =IF(C248="MATERIAS INSTITUCIONALES",1,0) -> 0 | I248: =CONCATENATE(A248,",'",B248,"','",C248,"','",D248,",'",E248,"','",F248,"','",G248,"',",H248) -> 1247,'LICENCIATURA','INGENIERÍA EN INTELIGENCIA ARTIFICIAL','IA 2°','MARTINEZ ALVARADO JUAN CARLOS','CÁLCULO MULTIVARIABLE','MASCULINO',0 | J248: =CONCATENATE($I$1,I248,");") -> INSERT INTO profesores (id,nivel,carrera,grupo,nombre,materia,sexo,sello) VALUES (1247,'LICENCIATURA','INGENIERÍA EN INTELIGENCIA ARTIFICIAL','IA 2°','MARTINEZ ALVARADO JUAN CARLOS','CÁLCULO MULTIVARIABLE','MASCULINO',0);
A249: =A248+1 -> 1248 | B249: LICENCIATURA | C249: =Hoja1!B249 -> INGENIERÍA EN INTELIGENCIA ARTIFICIAL | D249: IA 2°' | E249: =Hoja1!D249 -> RIZO DOMINGUEZ LUIS | F249: =Hoja1!E249 -> REPRESENTACION DEL CONOCIMIENTO | G249: =Hoja1!F249 -> MASCULINO | H249: =IF(C249="MATERIAS INSTITUCIONALES",1,0) -> 0 | I249: =CONCATENATE(A249,",'",B249,"','",C249,"','",D249,",'",E249,"','",F249,"','",G249,"',",H249) -> 1248,'LICENCIATURA','INGENIERÍA EN INTELIGENCIA ARTIFICIAL','IA 2°','RIZO DOMINGUEZ LUIS','REPRESENTACION DEL CONOCIMIENTO ','MASCULINO',0 | J249: =CONCATENATE($I$1,I249,");") -> INSERT INTO profesores (id,nivel,carrera,grupo,nombre,materia,sexo,sello) VALUES (1248,'LICENCIATURA','INGENIERÍA EN INTELIGENCIA ARTIFICIAL','IA 2°','RIZO DOMINGUEZ LUIS','REPRESENTACION DEL CONOCIMIENTO ','MASCULINO',0);
A250: =A249+1 -> 1249 | B250: LICENCIATURA | C250: =Hoja1!B250 -> INGENIERÍA EN INTELIGENCIA ARTIFICIAL | D250: IA 2°' | E250: =Hoja1!D250 -> SALDIVAR OROZCO EMMANUEL | F250: =Hoja1!E250 -> PROBABILIDAD Y ESTADISTICA APLICADA | G250: =Hoja1!F250 -> MASCULINO | H250: =IF(C250="MATERIAS INSTITUCIONALES",1,0) -> 0 | I250: =CONCATENATE(A250,",'",B250,"','",C250,"','",D250,",'",E250,"','",F250,"','",G250,"',",H250) -> 1249,'LICENCIATURA','INGENIERÍA EN INTELIGENCIA ARTIFICIAL','IA 2°','SALDIVAR OROZCO EMMANUEL','PROBABILIDAD Y ESTADISTICA APLICADA ','MASCULINO',0 | J250: =CONCATENATE($I$1,I250,");") -> INSERT INTO profesores (id,nivel,carrera,grupo,nombre,materia,sexo,sello) VALUES (1249,'LICENCIATURA','INGENIERÍA EN INTELIGENCIA ARTIFICIAL','IA 2°','SALDIVAR OROZCO EMMANUEL','PROBABILIDAD Y ESTADISTICA APLICADA ','MASCULINO',0);
A251: =A250+1 -> 1250 | B251: LICENCIATURA | C251: =Hoja1!B251 -> INGENIERÍA EN INTELIGENCIA ARTIFICIAL | D251: IA 2°' | E251: =Hoja1!D251 -> SANCHEZ OCAMPO EDUARDO FRANCISCO | F251: =Hoja1!E251 -> ELECTRÓNICA | G251: =Hoja1!F251 -> MASCULINO | H251: =IF(C251="MATERIAS INSTITUCIONALES",1,0) -> 0 | I251: =CONCATENATE(A251,",'",B251,"','",C251,"','",D251,",'",E251,"','",F251,"','",G251,"',",H251) -> 1250,'LICENCIATURA','INGENIERÍA EN INTELIGENCIA ARTIFICIAL','IA 2°','SANCHEZ OCAMPO EDUARDO FRANCISCO','ELECTRÓNICA ','MASCULINO',0 | J251: =CONCATENATE($I$1,I251,");") -> INSERT INTO profesores (id,nivel,carrera,grupo,nombre,materia,sexo,sello) VALUES (1250,'LICENCIATURA','INGENIERÍA EN INTELIGENCIA ARTIFICIAL','IA 2°','SANCHEZ OCAMPO EDUARDO FRANCISCO','ELECTRÓNICA ','MASCULINO',0);
A252: =A251+1 -> 1251 | B252: LICENCIATURA | C252: =Hoja1!B252 -> INGENIERÍA EN INTELIGENCIA ARTIFICIAL | D252: IA 4°' | E252: =Hoja1!D252 -> ANGUIANO SUAREZ DEL REAL RAFAEL DE JESUS | F252: =Hoja1!E252 -> PROGRAMACIÓN PARA ENTORNOS VIRTUALES | G252: =Hoja1!F252 -> MASCULINO | H252: =IF(C252="MATERIAS INSTITUCIONALES",1,0) -> 0 | I252: =CONCATENATE(A252,",'",B252,"','",C252,"','",D252,",'",E252,"','",F252,"','",G252,"',",H252) -> 1251,'LICENCIATURA','INGENIERÍA EN INTELIGENCIA ARTIFICIAL','IA 4°','ANGUIANO SUAREZ DEL REAL RAFAEL DE JESUS','PROGRAMACIÓN PARA ENTORNOS VIRTUALES ','MASCULINO',0 | J252: =CONCATENATE($I$1,I252,");") -> INSERT INTO profesores (id,nivel,carrera,grupo,nombre,materia,sexo,sello) VALUES (1251,'LICENCIATURA','INGENIERÍA EN INTELIGENCIA ARTIFICIAL','IA 4°','ANGUIANO SUAREZ DEL REAL RAFAEL DE JESUS','PROGRAMACIÓN PARA ENTORNOS VIRTUALES ','MASCULINO',0);
...
